{
  "symbol": "LRCX",
  "latest_price": 141.715,
  "as_of": "2025-10-19T15:02:38.150987+00:00",
  "resistances": [
    {
      "type": "52_week_high",
      "level": 153.695,
      "distance": 8.45,
      "strength_score": 9.5,
      "notes": "Primer test (pendiente)",
      "meta": {
        "level_date": "2025-10-06",
        "atr10": 6.7437,
        "tolerance": 1.3487,
        "retests_since_origin": 0,
        "testing_now": false,
        "touch_prob_1w": {
          "sigma_pct": 7.69,
          "sigma_source": "em_pct_1w",
          "z": 1.099
        }
      },
      "prob_touch_1w_pct": 13.6,
      "unit": "pct"
    }
  ],
  "supports": [
    {
      "type": "52_week_low",
      "level": 56.32,
      "distance": 60.26,
      "strength_score": 9.5,
      "notes": "Primer test (pendiente)",
      "meta": {
        "level_date": "2025-04-07",
        "atr10": 6.7437,
        "tolerance": 1.3487,
        "retests_since_origin": 0,
        "testing_now": false,
        "touch_prob_1w": {
          "sigma_pct": 7.69,
          "sigma_source": "em_pct_1w",
          "z": 7.836
        }
      },
      "prob_touch_1w_pct": 0.0,
      "unit": "pct"
    },
    {
      "type": "range_bottom_3_6m",
      "level": 96.32,
      "distance": 32.03,
      "strength_score": 8.5,
      "notes": "Suelo de rango 3–6m con 3 toques; último 2025-08-21 (pendiente)",
      "meta": {
        "first_touch_date": "2025-07-16",
        "last_touch_date": "2025-08-21",
        "touches": 3,
        "vol_factor_vs_median": 1.13,
        "tolerance": 1.3487,
        "testing_now": false,
        "touch_prob_1w": {
          "sigma_pct": 7.69,
          "sigma_source": "em_pct_1w",
          "z": 4.165
        }
      },
      "prob_touch_1w_pct": 0.0,
      "unit": "pct"
    },
    {
      "type": "gap_up_lower",
      "level": 128.76,
      "distance": 9.14,
      "strength_score": 7.5,
      "notes": "Gap alcista del 2025-09-29 (tam. 1.6%); abierto (pendiente)",
      "meta": {
        "gap_date": "2025-09-29",
        "gap_upper": 131.03,
        "gap_lower": 128.76,
        "gap_size": 2.27,
        "gap_size_pct_vs_price": 1.6,
        "vol_factor_vs_median": 1.02,
        "touches_since_gap": 0,
        "last_touch_date": null,
        "tolerance": 1.3487,
        "testing_now": false,
        "filled": false,
        "touch_prob_1w": {
          "sigma_pct": 7.69,
          "sigma_source": "em_pct_1w",
          "z": 1.189
        }
      },
      "prob_touch_1w_pct": 11.7,
      "unit": "pct"
    },
    {
      "type": "avwap_event_support",
      "level": 105.32,
      "distance": 25.68,
      "strength_score": 9.0,
      "notes": "AVWAP anclado a gap-up del 2025-05-12 (pendiente)",
      "meta": {
        "anchor_type": "gap_up",
        "anchor_date": "2025-05-12",
        "vol_factor_vs_median": 1.61,
        "gap_size_atr": 0.65,
        "touches": null,
        "tolerance": 1.3487,
        "testing_now": false,
        "min_distance_pct": 0.05,
        "method": "daily_typical_price_vwap",
        "touch_prob_1w": {
          "sigma_pct": 7.69,
          "sigma_source": "em_pct_1w",
          "z": 3.339
        }
      },
      "prob_touch_1w_pct": 0.0,
      "unit": "pct"
    },
    {
      "type": "put_wall_gamma",
      "level": 133.0,
      "distance": 6.15,
      "unit": "pct",
      "strength_score": 8.8,
      "notes": "Put wall (γ-$) exp 2025-11-07; dominante (15.7% del lado put) — pendiente",
      "meta": {
        "expiration": "2025-11-07",
        "gamma_usd": 0.009,
        "gamma_usd_units": "millions",
        "gamma_usd_total_puts": 0.058,
        "gamma_usd_share_pct": 15.7,
        "oi": 2592,
        "oi_share_pct": 14.4,
        "atr10": 6.7437,
        "tolerance": 1.3487,
        "window": "puts agregadas en top 3 expiraciones; sin filtro de distancia",
        "testing_now": false,
        "cluster": {
          "neighbors": [
            127.0,
            128.0,
            129.0,
            130.0,
            131.0,
            132.0,
            133.0,
            134.0,
            135.0,
            136.0,
            137.0,
            138.0,
            139.0
          ],
          "cluster_gamma_usd": 0.033,
          "cluster_share_pct": 57.0
        },
        "method": "sum(|γ|·OI·spot²) por strike multi-exp (sin límites de distancia)",
        "touch_prob_1w": {
          "sigma_pct": 7.69,
          "sigma_source": "em_pct_1w",
          "z": 0.8
        }
      },
      "prob_touch_1w_pct": 21.2
    }
  ],
  "relative_strength": {
    "vs_spy": {
      "20d_diff_pct": 11.39,
      "60d_diff_pct": 40.0
    }
  },
  "call_walls_top": [
    {
      "level": 143.0,
      "expiration": "2025-10-31",
      "gamma_usd_millions": 0.01,
      "gamma_share_pct": 15.8,
      "oi": 2157,
      "oi_share_pct": 13.4,
      "cluster_neighbors": [
        137.0,
        138.0,
        139.0,
        140.0,
        141.0,
        142.0,
        143.0,
        144.0,
        145.0,
        146.0,
        147.0,
        148.0,
        149.0
      ],
      "cluster_gamma_usd": 0.037,
      "cluster_share_pct": 57.8,
      "distance": 0.91
    },
    {
      "level": 150.0,
      "expiration": "2025-10-24",
      "gamma_usd_millions": 0.006,
      "gamma_share_pct": 9.5,
      "oi": 1338,
      "oi_share_pct": 8.3,
      "cluster_neighbors": [
        144.0,
        145.0,
        146.0,
        147.0,
        148.0,
        149.0,
        150.0,
        152.5,
        155.0
      ],
      "cluster_gamma_usd": 0.025,
      "cluster_share_pct": 38.4,
      "distance": 5.85
    },
    {
      "level": 140.0,
      "expiration": "2025-10-24",
      "gamma_usd_millions": 0.006,
      "gamma_share_pct": 9.4,
      "oi": 1087,
      "oi_share_pct": 6.7,
      "cluster_neighbors": [
        134.0,
        135.0,
        136.0,
        137.0,
        138.0,
        139.0,
        140.0,
        141.0,
        142.0,
        143.0,
        144.0,
        145.0,
        146.0
      ],
      "cluster_gamma_usd": 0.037,
      "cluster_share_pct": 57.8,
      "distance": -1.21
    },
    {
      "level": 135.0,
      "expiration": "2025-10-24",
      "gamma_usd_millions": 0.006,
      "gamma_share_pct": 8.7,
      "oi": 1178,
      "oi_share_pct": 7.3,
      "cluster_neighbors": [
        129.0,
        130.0,
        131.0,
        132.0,
        133.0,
        134.0,
        135.0,
        136.0,
        137.0,
        138.0,
        139.0,
        140.0,
        141.0
      ],
      "cluster_gamma_usd": 0.021,
      "cluster_share_pct": 31.9,
      "distance": -4.74
    },
    {
      "level": 145.0,
      "expiration": "2025-10-24",
      "gamma_usd_millions": 0.005,
      "gamma_share_pct": 7.7,
      "oi": 897,
      "oi_share_pct": 5.6,
      "cluster_neighbors": [
        139.0,
        140.0,
        141.0,
        142.0,
        143.0,
        144.0,
        145.0,
        146.0,
        147.0,
        148.0,
        149.0,
        150.0
      ],
      "cluster_gamma_usd": 0.041,
      "cluster_share_pct": 63.8,
      "distance": 2.32
    }
  ],
  "put_walls_top": [
    {
      "level": 133.0,
      "expiration": "2025-11-07",
      "gamma_usd_millions": 0.009,
      "gamma_share_pct": 15.7,
      "oi": 2592,
      "oi_share_pct": 14.4,
      "cluster_neighbors": [
        127.0,
        128.0,
        129.0,
        130.0,
        131.0,
        132.0,
        133.0,
        134.0,
        135.0,
        136.0,
        137.0,
        138.0,
        139.0
      ],
      "cluster_gamma_usd": 0.033,
      "cluster_share_pct": 57.0,
      "distance": -6.15
    },
    {
      "level": 137.0,
      "expiration": "2025-10-24",
      "gamma_usd_millions": 0.006,
      "gamma_share_pct": 10.4,
      "oi": 1162,
      "oi_share_pct": 6.5,
      "cluster_neighbors": [
        131.0,
        132.0,
        133.0,
        134.0,
        135.0,
        136.0,
        137.0,
        138.0,
        139.0,
        140.0,
        141.0,
        142.0,
        143.0
      ],
      "cluster_gamma_usd": 0.032,
      "cluster_share_pct": 54.4,
      "distance": -3.33
    },
    {
      "level": 128.0,
      "expiration": "2025-10-24",
      "gamma_usd_millions": 0.005,
      "gamma_share_pct": 8.0,
      "oi": 1485,
      "oi_share_pct": 8.3,
      "cluster_neighbors": [
        122.0,
        123.0,
        124.0,
        125.0,
        126.0,
        127.0,
        128.0,
        129.0,
        130.0,
        131.0,
        132.0,
        133.0,
        134.0
      ],
      "cluster_gamma_usd": 0.024,
      "cluster_share_pct": 40.8,
      "distance": -9.68
    },
    {
      "level": 145.0,
      "expiration": "2025-10-24",
      "gamma_usd_millions": 0.004,
      "gamma_share_pct": 7.6,
      "oi": 790,
      "oi_share_pct": 4.4,
      "cluster_neighbors": [
        139.0,
        140.0,
        141.0,
        142.0,
        143.0,
        144.0,
        145.0,
        146.0,
        147.0,
        148.0,
        149.0,
        150.0
      ],
      "cluster_gamma_usd": 0.015,
      "cluster_share_pct": 26.6,
      "distance": 2.32
    },
    {
      "level": 135.0,
      "expiration": "2025-10-24",
      "gamma_usd_millions": 0.004,
      "gamma_share_pct": 7.2,
      "oi": 915,
      "oi_share_pct": 5.1,
      "cluster_neighbors": [
        129.0,
        130.0,
        131.0,
        132.0,
        133.0,
        134.0,
        135.0,
        136.0,
        137.0,
        138.0,
        139.0,
        140.0,
        141.0
      ],
      "cluster_gamma_usd": 0.032,
      "cluster_share_pct": 54.2,
      "distance": -4.74
    }
  ],
  "technicals": {
    "rsi14": 58.79,
    "sma": {
      "20": 137.934,
      "50": 119.0902,
      "200": 91.6798
    },
    "bollinger20_2": {
      "upper": 151.089,
      "middle": 137.934,
      "lower": 124.779,
      "width_pct": 19.07,
      "method": "SMA20 ± 2·σ(cierre)"
    },
    "keltner_ema20_atr10": {
      "upper": 152.1454,
      "center": 138.6579,
      "lower": 125.1704,
      "mult": 2.0,
      "method": "EMA20(typical) ± mult·ATR10"
    },
    "donchian20": {
      "high": 153.695,
      "low": 125.0201
    },
    "atr10": 6.7437,
    "volume": {
      "avg_20d": 11760840.4,
      "median_20d": 11116296.5,
      "avg_dollar_20d": 1622455261.08,
      "last_complete_day": {
        "date": "2025-10-17",
        "shares": 6389799,
        "rel_to_20d": 0.543
      },
      "series": {
        "shares_20d": [
          13403746,
          12051102,
          12435947,
          9621715,
          8788993,
          11015536,
          10328761,
          15549117,
          16417073,
          8970274,
          11217057,
          16549789,
          13695736,
          8102517,
          18748964,
          10048074,
          10509662,
          9722650,
          11650296,
          6389799
        ],
        "dollar_volume_20d": [
          1771975221.2,
          1589901886.86,
          1595780719.04,
          1232830342.95,
          1127891471.69,
          1444026614.24,
          1383021097.9,
          2220258416.43,
          2413145560.27,
          1307955651.94,
          1673024051.55,
          2322762886.15,
          1952190209.44,
          1142454897.0,
          2463051400.68,
          1384725077.94,
          1453591351.22,
          1407645267.0,
          1658652641.52,
          904220456.49
        ]
      },
      "current_session": {
        "shares": 6389799.0,
        "comparable_to_avg_20d": false
      },
      "note": "ratios calculados contra último día COMPLETO; intradía solo informativo"
    },
    "trend": {
      "above_sma200": true,
      "price_vs_sma": {
        "20": 2.59,
        "50": 18.83,
        "200": 54.35
      },
      "price_20d_change_pct": 11.5,
      "price_50d_change_pct": 42.72,
      "bollinger_pos_pct": 63.6
    }
  },
  "options": {
    "expected_move_1w": {
      "expiration": "2025-10-24",
      "dollars": 10.9,
      "percent": 7.69,
      "method": "ATM straddle mid-price (call+put) en expiración ~1W"
    },
    "max_pain": {
      "expiration": "2025-10-24",
      "strike": 137.0
    },
    "dealer_gamma": {
      "gex_total_usd_millions": 0.006,
      "gamma_regime": "positive",
      "method": "sum_calls_minus_puts"
    },
    "summary_by_expiration": [
      {
        "date": "2025-10-24",
        "dte": 5,
        "atm_iv": 0.8215,
        "expected_move": {
          "dollars": 10.9,
          "percent": 0.0769,
          "method": "ATM straddle mid"
        },
        "total_call_oi": 8613,
        "total_put_oi": 7593,
        "put_call_oi_ratio": 0.882
      },
      {
        "date": "2025-10-31",
        "dte": 12,
        "atm_iv": 0.7127,
        "expected_move": {
          "dollars": 14.65,
          "percent": 0.1034,
          "method": "ATM straddle mid"
        },
        "total_call_oi": 6052,
        "total_put_oi": 4468,
        "put_call_oi_ratio": 0.738
      },
      {
        "date": "2025-11-07",
        "dte": 19,
        "atm_iv": 0.6089,
        "expected_move": {
          "dollars": 15.75,
          "percent": 0.1111,
          "method": "ATM straddle mid"
        },
        "total_call_oi": 1477,
        "total_put_oi": 5928,
        "put_call_oi_ratio": 4.014
      }
    ],
    "max_pain_by_expiration": [
      {
        "date": "2025-10-24",
        "strike": 137.0,
        "confidence": 0.001
      },
      {
        "date": "2025-10-31",
        "strike": 135.0,
        "confidence": 0.0
      },
      {
        "date": "2025-11-07",
        "strike": 138.0,
        "confidence": 0.0
      }
    ]
  },
  "options_overview": {
    "put_call_oi_ratio": {
      "near_term": {
        "scope": "near_term",
        "expirations_considered": [
          "2025-10-24",
          "2025-10-31",
          "2025-11-07"
        ],
        "total_put_oi": 17989,
        "total_call_oi": 16142,
        "ratio": 1.114,
        "dte_buckets": {
          "0_7": {
            "puts": 7593,
            "calls": 8613,
            "ratio": 0.882,
            "expirations": [
              "2025-10-24"
            ]
          },
          "8_30": {
            "puts": 10396,
            "calls": 7529,
            "ratio": 1.381,
            "expirations": [
              "2025-10-31",
              "2025-11-07"
            ]
          },
          "31_60": {
            "puts": 0,
            "calls": 0,
            "ratio": null,
            "expirations": []
          },
          "61_plus": {
            "puts": 0,
            "calls": 0,
            "ratio": null,
            "expirations": []
          }
        },
        "per_expiration": [
          {
            "expiration": "2025-10-24",
            "dte": 5,
            "puts": 7593,
            "calls": 8613,
            "ratio": 0.882
          },
          {
            "expiration": "2025-10-31",
            "dte": 12,
            "puts": 4468,
            "calls": 6052,
            "ratio": 0.738
          },
          {
            "expiration": "2025-11-07",
            "dte": 19,
            "puts": 5928,
            "calls": 1477,
            "ratio": 4.014
          }
        ]
      },
      "thru_60d": {
        "scope": "thru_60d",
        "expirations_considered": [
          "2025-10-24",
          "2025-10-31",
          "2025-11-07",
          "2025-11-14",
          "2025-11-21",
          "2025-11-28"
        ],
        "total_put_oi": 31564,
        "total_call_oi": 41517,
        "ratio": 0.76,
        "dte_buckets": {
          "0_7": {
            "puts": 7593,
            "calls": 8613,
            "ratio": 0.882,
            "expirations": [
              "2025-10-24"
            ]
          },
          "8_30": {
            "puts": 12063,
            "calls": 8400,
            "ratio": 1.436,
            "expirations": [
              "2025-10-31",
              "2025-11-07",
              "2025-11-14"
            ]
          },
          "31_60": {
            "puts": 11908,
            "calls": 24504,
            "ratio": 0.486,
            "expirations": [
              "2025-11-21",
              "2025-11-28"
            ]
          },
          "61_plus": {
            "puts": 0,
            "calls": 0,
            "ratio": null,
            "expirations": []
          }
        },
        "per_expiration": [
          {
            "expiration": "2025-10-24",
            "dte": 5,
            "puts": 7593,
            "calls": 8613,
            "ratio": 0.882
          },
          {
            "expiration": "2025-10-31",
            "dte": 12,
            "puts": 4468,
            "calls": 6052,
            "ratio": 0.738
          },
          {
            "expiration": "2025-11-07",
            "dte": 19,
            "puts": 5928,
            "calls": 1477,
            "ratio": 4.014
          },
          {
            "expiration": "2025-11-14",
            "dte": 26,
            "puts": 1667,
            "calls": 871,
            "ratio": 1.914
          },
          {
            "expiration": "2025-11-21",
            "dte": 33,
            "puts": 11733,
            "calls": 24365,
            "ratio": 0.482
          },
          {
            "expiration": "2025-11-28",
            "dte": 40,
            "puts": 175,
            "calls": 139,
            "ratio": 1.259
          }
        ]
      },
      "default_scope": "near_term",
      "ratio": 1.114,
      "total_put_oi": 17989,
      "total_call_oi": 16142
    }
  },
  "vols": {
    "rv20_annual_pct": 52.738,
    "rv60_annual_pct": 43.978,
    "rv20_weekly_pct": 7.313,
    "rv60_weekly_pct": 6.099,
    "em_pct_1w": 7.69,
    "em_abs_1w": 10.9,
    "iv_to_rv_ratio": 1.051,
    "em_to_atr_ratio": 1.616,
    "windows": {
      "rv": [
        20,
        60
      ]
    },
    "units": {
      "rv_annual_pct": "percent",
      "rv_weekly_pct": "percent",
      "em_pct_1w": "percent",
      "em_abs_1w": "dollars"
    },
    "method": "std(log_returns_daily) * sqrt(252); weekly = annual/sqrt(52)"
  },
  "forward_returns": {
    "lookback_days": 252,
    "series": {
      "anchor_dates": [
        "2024-10-15",
        "2024-10-16",
        "2024-10-17",
        "2024-10-18",
        "2024-10-21",
        "2024-10-22",
        "2024-10-23",
        "2024-10-24",
        "2024-10-25",
        "2024-10-28",
        "2024-10-29",
        "2024-10-30",
        "2024-10-31",
        "2024-11-01",
        "2024-11-04",
        "2024-11-05",
        "2024-11-06",
        "2024-11-07",
        "2024-11-08",
        "2024-11-11",
        "2024-11-12",
        "2024-11-13",
        "2024-11-14",
        "2024-11-15",
        "2024-11-18",
        "2024-11-19",
        "2024-11-20",
        "2024-11-21",
        "2024-11-22",
        "2024-11-25",
        "2024-11-26",
        "2024-11-27",
        "2024-11-29",
        "2024-12-02",
        "2024-12-03",
        "2024-12-04",
        "2024-12-05",
        "2024-12-06",
        "2024-12-09",
        "2024-12-10",
        "2024-12-11",
        "2024-12-12",
        "2024-12-13",
        "2024-12-16",
        "2024-12-17",
        "2024-12-18",
        "2024-12-19",
        "2024-12-20",
        "2024-12-23",
        "2024-12-24",
        "2024-12-26",
        "2024-12-27",
        "2024-12-30",
        "2024-12-31",
        "2025-01-02",
        "2025-01-03",
        "2025-01-06",
        "2025-01-07",
        "2025-01-08",
        "2025-01-10",
        "2025-01-13",
        "2025-01-14",
        "2025-01-15",
        "2025-01-16",
        "2025-01-17",
        "2025-01-21",
        "2025-01-22",
        "2025-01-23",
        "2025-01-24",
        "2025-01-27",
        "2025-01-28",
        "2025-01-29",
        "2025-01-30",
        "2025-01-31",
        "2025-02-03",
        "2025-02-04",
        "2025-02-05",
        "2025-02-06",
        "2025-02-07",
        "2025-02-10",
        "2025-02-11",
        "2025-02-12",
        "2025-02-13",
        "2025-02-14",
        "2025-02-18",
        "2025-02-19",
        "2025-02-20",
        "2025-02-21",
        "2025-02-24",
        "2025-02-25",
        "2025-02-26",
        "2025-02-27",
        "2025-02-28",
        "2025-03-03",
        "2025-03-04",
        "2025-03-05",
        "2025-03-06",
        "2025-03-07",
        "2025-03-10",
        "2025-03-11",
        "2025-03-12",
        "2025-03-13",
        "2025-03-14",
        "2025-03-17",
        "2025-03-18",
        "2025-03-19",
        "2025-03-20",
        "2025-03-21",
        "2025-03-24",
        "2025-03-25",
        "2025-03-26",
        "2025-03-27",
        "2025-03-28",
        "2025-03-31",
        "2025-04-01",
        "2025-04-02",
        "2025-04-03",
        "2025-04-04",
        "2025-04-07",
        "2025-04-08",
        "2025-04-09",
        "2025-04-10",
        "2025-04-11",
        "2025-04-14",
        "2025-04-15",
        "2025-04-16",
        "2025-04-17",
        "2025-04-21",
        "2025-04-22",
        "2025-04-23",
        "2025-04-24",
        "2025-04-25",
        "2025-04-28",
        "2025-04-29",
        "2025-04-30",
        "2025-05-01",
        "2025-05-02",
        "2025-05-05",
        "2025-05-06",
        "2025-05-07",
        "2025-05-08",
        "2025-05-09",
        "2025-05-12",
        "2025-05-13",
        "2025-05-14",
        "2025-05-15",
        "2025-05-16",
        "2025-05-19",
        "2025-05-20",
        "2025-05-21",
        "2025-05-22",
        "2025-05-23",
        "2025-05-27",
        "2025-05-28",
        "2025-05-29",
        "2025-05-30",
        "2025-06-02",
        "2025-06-03",
        "2025-06-04",
        "2025-06-05",
        "2025-06-06",
        "2025-06-09",
        "2025-06-10",
        "2025-06-11",
        "2025-06-12",
        "2025-06-13",
        "2025-06-16",
        "2025-06-17",
        "2025-06-18",
        "2025-06-20",
        "2025-06-23",
        "2025-06-24",
        "2025-06-25",
        "2025-06-26",
        "2025-06-27",
        "2025-06-30",
        "2025-07-01",
        "2025-07-02",
        "2025-07-03",
        "2025-07-07",
        "2025-07-08",
        "2025-07-09",
        "2025-07-10",
        "2025-07-11",
        "2025-07-14",
        "2025-07-15",
        "2025-07-16",
        "2025-07-17",
        "2025-07-18",
        "2025-07-21",
        "2025-07-22",
        "2025-07-23",
        "2025-07-24",
        "2025-07-25",
        "2025-07-28",
        "2025-07-29",
        "2025-07-30",
        "2025-07-31",
        "2025-08-01",
        "2025-08-04",
        "2025-08-05",
        "2025-08-06",
        "2025-08-07",
        "2025-08-08",
        "2025-08-11",
        "2025-08-12",
        "2025-08-13",
        "2025-08-14",
        "2025-08-15",
        "2025-08-18",
        "2025-08-19",
        "2025-08-20",
        "2025-08-21",
        "2025-08-22",
        "2025-08-25",
        "2025-08-26",
        "2025-08-27",
        "2025-08-28",
        "2025-08-29",
        "2025-09-02",
        "2025-09-03",
        "2025-09-04",
        "2025-09-05",
        "2025-09-08",
        "2025-09-09",
        "2025-09-10",
        "2025-09-11",
        "2025-09-12",
        "2025-09-15",
        "2025-09-16",
        "2025-09-17",
        "2025-09-18",
        "2025-09-19",
        "2025-09-22",
        "2025-09-23",
        "2025-09-24",
        "2025-09-25",
        "2025-09-26",
        "2025-09-29",
        "2025-09-30",
        "2025-10-01",
        "2025-10-02",
        "2025-10-03",
        "2025-10-06",
        "2025-10-07",
        "2025-10-08",
        "2025-10-09",
        "2025-10-10",
        "2025-10-13",
        "2025-10-14",
        "2025-10-15",
        "2025-10-16"
      ],
      "t1_dates": [
        "2024-10-16",
        "2024-10-17",
        "2024-10-18",
        "2024-10-21",
        "2024-10-22",
        "2024-10-23",
        "2024-10-24",
        "2024-10-25",
        "2024-10-28",
        "2024-10-29",
        "2024-10-30",
        "2024-10-31",
        "2024-11-01",
        "2024-11-04",
        "2024-11-05",
        "2024-11-06",
        "2024-11-07",
        "2024-11-08",
        "2024-11-11",
        "2024-11-12",
        "2024-11-13",
        "2024-11-14",
        "2024-11-15",
        "2024-11-18",
        "2024-11-19",
        "2024-11-20",
        "2024-11-21",
        "2024-11-22",
        "2024-11-25",
        "2024-11-26",
        "2024-11-27",
        "2024-11-29",
        "2024-12-02",
        "2024-12-03",
        "2024-12-04",
        "2024-12-05",
        "2024-12-06",
        "2024-12-09",
        "2024-12-10",
        "2024-12-11",
        "2024-12-12",
        "2024-12-13",
        "2024-12-16",
        "2024-12-17",
        "2024-12-18",
        "2024-12-19",
        "2024-12-20",
        "2024-12-23",
        "2024-12-24",
        "2024-12-26",
        "2024-12-27",
        "2024-12-30",
        "2024-12-31",
        "2025-01-02",
        "2025-01-03",
        "2025-01-06",
        "2025-01-07",
        "2025-01-08",
        "2025-01-10",
        "2025-01-13",
        "2025-01-14",
        "2025-01-15",
        "2025-01-16",
        "2025-01-17",
        "2025-01-21",
        "2025-01-22",
        "2025-01-23",
        "2025-01-24",
        "2025-01-27",
        "2025-01-28",
        "2025-01-29",
        "2025-01-30",
        "2025-01-31",
        "2025-02-03",
        "2025-02-04",
        "2025-02-05",
        "2025-02-06",
        "2025-02-07",
        "2025-02-10",
        "2025-02-11",
        "2025-02-12",
        "2025-02-13",
        "2025-02-14",
        "2025-02-18",
        "2025-02-19",
        "2025-02-20",
        "2025-02-21",
        "2025-02-24",
        "2025-02-25",
        "2025-02-26",
        "2025-02-27",
        "2025-02-28",
        "2025-03-03",
        "2025-03-04",
        "2025-03-05",
        "2025-03-06",
        "2025-03-07",
        "2025-03-10",
        "2025-03-11",
        "2025-03-12",
        "2025-03-13",
        "2025-03-14",
        "2025-03-17",
        "2025-03-18",
        "2025-03-19",
        "2025-03-20",
        "2025-03-21",
        "2025-03-24",
        "2025-03-25",
        "2025-03-26",
        "2025-03-27",
        "2025-03-28",
        "2025-03-31",
        "2025-04-01",
        "2025-04-02",
        "2025-04-03",
        "2025-04-04",
        "2025-04-07",
        "2025-04-08",
        "2025-04-09",
        "2025-04-10",
        "2025-04-11",
        "2025-04-14",
        "2025-04-15",
        "2025-04-16",
        "2025-04-17",
        "2025-04-21",
        "2025-04-22",
        "2025-04-23",
        "2025-04-24",
        "2025-04-25",
        "2025-04-28",
        "2025-04-29",
        "2025-04-30",
        "2025-05-01",
        "2025-05-02",
        "2025-05-05",
        "2025-05-06",
        "2025-05-07",
        "2025-05-08",
        "2025-05-09",
        "2025-05-12",
        "2025-05-13",
        "2025-05-14",
        "2025-05-15",
        "2025-05-16",
        "2025-05-19",
        "2025-05-20",
        "2025-05-21",
        "2025-05-22",
        "2025-05-23",
        "2025-05-27",
        "2025-05-28",
        "2025-05-29",
        "2025-05-30",
        "2025-06-02",
        "2025-06-03",
        "2025-06-04",
        "2025-06-05",
        "2025-06-06",
        "2025-06-09",
        "2025-06-10",
        "2025-06-11",
        "2025-06-12",
        "2025-06-13",
        "2025-06-16",
        "2025-06-17",
        "2025-06-18",
        "2025-06-20",
        "2025-06-23",
        "2025-06-24",
        "2025-06-25",
        "2025-06-26",
        "2025-06-27",
        "2025-06-30",
        "2025-07-01",
        "2025-07-02",
        "2025-07-03",
        "2025-07-07",
        "2025-07-08",
        "2025-07-09",
        "2025-07-10",
        "2025-07-11",
        "2025-07-14",
        "2025-07-15",
        "2025-07-16",
        "2025-07-17",
        "2025-07-18",
        "2025-07-21",
        "2025-07-22",
        "2025-07-23",
        "2025-07-24",
        "2025-07-25",
        "2025-07-28",
        "2025-07-29",
        "2025-07-30",
        "2025-07-31",
        "2025-08-01",
        "2025-08-04",
        "2025-08-05",
        "2025-08-06",
        "2025-08-07",
        "2025-08-08",
        "2025-08-11",
        "2025-08-12",
        "2025-08-13",
        "2025-08-14",
        "2025-08-15",
        "2025-08-18",
        "2025-08-19",
        "2025-08-20",
        "2025-08-21",
        "2025-08-22",
        "2025-08-25",
        "2025-08-26",
        "2025-08-27",
        "2025-08-28",
        "2025-08-29",
        "2025-09-02",
        "2025-09-03",
        "2025-09-04",
        "2025-09-05",
        "2025-09-08",
        "2025-09-09",
        "2025-09-10",
        "2025-09-11",
        "2025-09-12",
        "2025-09-15",
        "2025-09-16",
        "2025-09-17",
        "2025-09-18",
        "2025-09-19",
        "2025-09-22",
        "2025-09-23",
        "2025-09-24",
        "2025-09-25",
        "2025-09-26",
        "2025-09-29",
        "2025-09-30",
        "2025-10-01",
        "2025-10-02",
        "2025-10-03",
        "2025-10-06",
        "2025-10-07",
        "2025-10-08",
        "2025-10-09",
        "2025-10-10",
        "2025-10-13",
        "2025-10-14",
        "2025-10-15",
        "2025-10-16",
        "2025-10-17"
      ],
      "t1_close_from_close_pct": [
        -2.907,
        -1.349,
        -0.41,
        0.0,
        0.22,
        -0.192,
        5.092,
        1.45,
        -2.871,
        3.791,
        -2.375,
        -2.747,
        0.605,
        -0.842,
        3.007,
        0.497,
        3.165,
        -1.275,
        -2.596,
        -0.617,
        -2.444,
        1.273,
        -6.338,
        0.742,
        -0.567,
        -0.171,
        4.397,
        -0.67,
        1.473,
        -1.384,
        -1.541,
        3.228,
        6.267,
        -0.217,
        -0.102,
        -3.897,
        1.835,
        1.123,
        -2.995,
        4.126,
        -3.387,
        0.9,
        2.059,
        -0.026,
        -3.354,
        -5.306,
        0.814,
        2.8,
        0.041,
        0.217,
        -0.797,
        -1.703,
        0.111,
        0.291,
        3.686,
        3.821,
        -0.59,
        -0.619,
        -3.102,
        -0.268,
        0.819,
        1.452,
        4.032,
        1.363,
        1.494,
        2.147,
        -2.426,
        -1.908,
        -5.083,
        -1.481,
        0.859,
        7.425,
        0.396,
        -1.061,
        -0.349,
        2.54,
        1.086,
        -0.604,
        1.7,
        -0.561,
        -2.03,
        2.121,
        -0.66,
        4.628,
        1.247,
        1.551,
        -3.37,
        -3.116,
        -3.66,
        1.258,
        -6.31,
        0.748,
        -1.251,
        0.871,
        3.414,
        -3.264,
        3.322,
        -6.581,
        -0.61,
        4.403,
        -1.737,
        4.558,
        -0.483,
        -1.213,
        0.737,
        -0.488,
        -2.205,
        2.835,
        -0.41,
        -1.97,
        -1.747,
        -2.941,
        0.124,
        0.179,
        1.304,
        -11.602,
        -9.399,
        5.263,
        -3.135,
        18.025,
        -6.581,
        1.581,
        0.563,
        0.855,
        -4.822,
        -2.119,
        -2.149,
        1.747,
        5.12,
        6.249,
        0.733,
        0.21,
        -0.936,
        1.086,
        0.084,
        3.89,
        -0.819,
        -1.015,
        2.597,
        -0.213,
        0.614,
        9.143,
        3.647,
        -0.328,
        -0.212,
        -0.425,
        -0.722,
        0.561,
        -1.78,
        -0.278,
        -1.817,
        3.553,
        0.071,
        0.19,
        -4.004,
        2.092,
        1.431,
        1.327,
        0.165,
        1.696,
        2.258,
        3.058,
        -0.055,
        0.781,
        -2.335,
        4.345,
        -0.803,
        -0.453,
        -1.897,
        1.238,
        4.388,
        0.408,
        0.854,
        0.372,
        0.144,
        -0.544,
        2.087,
        -0.02,
        -0.678,
        1.722,
        -0.02,
        1.252,
        0.663,
        -2.074,
        1.456,
        -0.693,
        0.418,
        -0.129,
        1.073,
        -3.981,
        -0.604,
        0.7,
        -0.839,
        1.712,
        0.324,
        0.152,
        -4.289,
        1.613,
        2.117,
        -1.758,
        -0.765,
        3.346,
        2.622,
        0.246,
        3.216,
        1.387,
        0.6,
        -7.329,
        -0.633,
        1.466,
        -1.176,
        -0.746,
        1.697,
        1.199,
        2.32,
        0.039,
        0.405,
        -3.785,
        -3.115,
        0.732,
        2.742,
        2.519,
        2.059,
        0.476,
        1.696,
        7.656,
        1.194,
        1.924,
        1.057,
        1.187,
        3.626,
        0.475,
        4.16,
        -0.204,
        -2.736,
        -0.148,
        0.156,
        2.151,
        2.144,
        6.639,
        2.941,
        -0.803,
        2.291,
        -5.9,
        1.56,
        -1.08,
        -6.83,
        4.902,
        0.363,
        4.678,
        -1.665,
        -0.604
      ],
      "t1_high_from_close_pct": [
        1.493,
        3.318,
        1.49,
        0.357,
        0.776,
        0.637,
        6.341,
        3.957,
        0.451,
        4.361,
        -1.417,
        -0.458,
        1.506,
        0.241,
        3.526,
        2.212,
        3.497,
        0.189,
        -0.396,
        0.656,
        -0.834,
        2.424,
        -2.781,
        1.071,
        -0.071,
        0.065,
        4.854,
        0.191,
        1.914,
        1.031,
        0.248,
        5.868,
        6.734,
        0.242,
        1.901,
        -0.486,
        1.968,
        2.167,
        1.033,
        4.778,
        -1.112,
        2.302,
        2.446,
        1.169,
        1.928,
        -3.045,
        3.181,
        3.064,
        0.501,
        0.989,
        -0.311,
        -1.104,
        0.901,
        2.337,
        3.914,
        6.71,
        2.77,
        0.297,
        -1.051,
        -0.094,
        0.913,
        2.944,
        8.772,
        3.269,
        2.653,
        4.528,
        -2.234,
        0.579,
        -3.577,
        0.053,
        3.999,
        9.235,
        4.317,
        0.629,
        0.493,
        2.747,
        1.361,
        0.821,
        2.842,
        0.92,
        -1.345,
        2.562,
        0.372,
        4.906,
        3.719,
        4.632,
        1.348,
        0.802,
        0.432,
        3.288,
        1.064,
        2.639,
        3.922,
        3.55,
        3.885,
        -0.612,
        3.943,
        -2.063,
        2.134,
        5.862,
        0.888,
        5.076,
        0.572,
        -0.6,
        2.74,
        0.218,
        -1.522,
        3.877,
        0.489,
        0.245,
        -0.092,
        0.655,
        0.331,
        0.206,
        2.71,
        -4.378,
        -3.297,
        11.863,
        6.286,
        19.286,
        -4.374,
        2.303,
        2.786,
        2.479,
        -2.367,
        0.368,
        -1.71,
        2.613,
        7.136,
        6.714,
        1.953,
        0.728,
        0.126,
        1.326,
        2.595,
        5.242,
        0.51,
        -0.047,
        2.918,
        1.812,
        1.869,
        9.541,
        4.292,
        0.927,
        0.341,
        -0.389,
        0.024,
        0.632,
        0.581,
        1.244,
        -1.423,
        3.769,
        1.293,
        2.69,
        -0.416,
        2.154,
        1.855,
        1.65,
        1.852,
        3.145,
        3.451,
        3.477,
        1.088,
        1.045,
        -0.469,
        4.535,
        1.718,
        1.014,
        1.29,
        2.509,
        4.541,
        1.82,
        0.943,
        1.219,
        0.484,
        -0.026,
        2.211,
        0.678,
        0.111,
        2.186,
        1.257,
        1.844,
        0.955,
        -0.718,
        2.58,
        -0.643,
        1.001,
        0.933,
        1.917,
        -0.606,
        0.706,
        1.565,
        -0.46,
        2.651,
        1.622,
        1.728,
        -3.492,
        1.919,
        2.532,
        0.955,
        -0.217,
        4.43,
        3.101,
        2.359,
        3.569,
        2.099,
        1.199,
        -1.392,
        0.291,
        1.77,
        0.683,
        0.706,
        4.207,
        1.669,
        2.676,
        0.14,
        1.186,
        -1.345,
        -2.881,
        0.85,
        3.448,
        2.579,
        3.322,
        0.714,
        2.093,
        7.955,
        1.661,
        2.026,
        1.476,
        2.333,
        5.574,
        1.172,
        4.499,
        1.033,
        -1.292,
        0.577,
        0.492,
        3.92,
        2.38,
        6.863,
        3.194,
        0.626,
        5.408,
        0.142,
        1.803,
        0.224,
        0.567,
        5.732,
        2.257,
        4.996,
        1.934,
        0.197
      ],
      "t1_close_from_open_pct": [
        -3.901,
        -4.342,
        -1.873,
        0.303,
        0.454,
        0.677,
        0.512,
        0.271,
        -2.223,
        3.243,
        -0.533,
        -2.3,
        0.592,
        -0.349,
        2.523,
        -1.159,
        1.473,
        -0.799,
        -1.627,
        -0.936,
        -0.872,
        -0.875,
        -2.233,
        0.973,
        0.171,
        0.057,
        2.725,
        0.048,
        -0.409,
        -1.916,
        -1.595,
        0.041,
        6.267,
        0.824,
        -1.609,
        -3.428,
        1.93,
        1.288,
        -3.852,
        2.503,
        -2.162,
        -0.157,
        2.045,
        -0.103,
        -3.639,
        -2.117,
        1.772,
        2.004,
        -0.317,
        1.01,
        0.136,
        0.208,
        -0.235,
        -0.371,
        2.637,
        1.037,
        -1.699,
        -0.491,
        -1.802,
        1.749,
        0.027,
        0.382,
        0.418,
        -1.363,
        0.841,
        0.995,
        0.594,
        -2.472,
        -1.511,
        -0.799,
        -2.97,
        1.229,
        -0.049,
        1.538,
        1.152,
        3.59,
        2.07,
        -1.034,
        0.215,
        0.241,
        0.357,
        2.115,
        0.121,
        1.967,
        1.576,
        -1.067,
        -4.038,
        -3.597,
        -3.335,
        -0.477,
        -6.712,
        -0.013,
        -2.765,
        0.539,
        2.983,
        -0.856,
        3.079,
        -4.018,
        -0.972,
        1.706,
        -1.123,
        2.521,
        1.556,
        -0.155,
        0.724,
        1.121,
        -0.211,
        0.322,
        -0.231,
        -2.071,
        -1.417,
        -2.707,
        1.536,
        1.097,
        2.872,
        -7.12,
        -5.471,
        7.39,
        -6.806,
        17.169,
        -2.302,
        2.725,
        -1.136,
        0.514,
        -0.153,
        -2.418,
        0.048,
        0.818,
        -0.12,
        1.765,
        1.55,
        0.874,
        0.014,
        4.035,
        -0.623,
        0.364,
        0.047,
        0.785,
        2.199,
        -1.577,
        -0.436,
        1.965,
        3.509,
        -0.2,
        0.665,
        0.024,
        1.354,
        0.91,
        -0.505,
        -0.097,
        1.173,
        1.084,
        0.03,
        -1.969,
        -3.442,
        2.352,
        1.937,
        0.665,
        -0.69,
        0.104,
        1.378,
        2.495,
        -0.476,
        1.148,
        0.845,
        2.705,
        -0.729,
        -0.865,
        -2.751,
        0.263,
        2.574,
        -0.239,
        0.582,
        0.17,
        -0.215,
        0.228,
        3.109,
        -0.02,
        -0.224,
        1.017,
        0.01,
        0.139,
        1.395,
        -0.945,
        -0.463,
        2.712,
        1.337,
        -0.573,
        0.852,
        -3.277,
        -1.181,
        0.215,
        0.269,
        -0.364,
        -0.453,
        -0.432,
        4.203,
        3.948,
        1.011,
        -2.126,
        -0.374,
        0.563,
        2.622,
        -1.829,
        2.562,
        0.225,
        1.111,
        -4.934,
        -0.121,
        1.518,
        -1.817,
        -0.354,
        1.04,
        1.3,
        2.3,
        0.485,
        0.087,
        -1.727,
        1.321,
        0.732,
        2.826,
        1.229,
        0.062,
        0.629,
        0.619,
        6.673,
        0.897,
        1.197,
        0.413,
        0.894,
        -0.182,
        0.447,
        1.849,
        1.68,
        -1.292,
        1.337,
        0.305,
        -1.495,
        1.945,
        7.839,
        0.017,
        -0.007,
        -0.5,
        -5.951,
        3.357,
        -0.529,
        -6.565,
        -0.203,
        3.139,
        0.542,
        -3.53,
        -0.527
      ]
    },
    "stats": {
      "close_from_close": {
        "count": 252,
        "mean": 0.289,
        "median": 0.218,
        "up_rate_pct": 55.56,
        "p05": -4.132,
        "p95": 4.589
      },
      "high_from_close": {
        "count": 252,
        "mean": 1.796,
        "median": 1.419,
        "up_rate_pct": 83.33,
        "p05": -1.467,
        "p95": 6.056
      },
      "close_from_open": {
        "count": 252,
        "mean": 0.171,
        "median": 0.171,
        "up_rate_pct": 57.14,
        "p05": -3.616,
        "p95": 3.123
      }
    },
    "latest": {
      "anchor_date": "2025-10-16",
      "t1_date": "2025-10-17",
      "close_from_close_pct": -0.604,
      "high_from_close_pct": 0.197,
      "close_from_open_pct": -0.527
    }
  },
  "conventions": {
    "returns": {
      "basis": "close_to_close",
      "intraday_high_basis": "close_to_high",
      "t_is_trading_days": true
    },
    "probabilities": {
      "touch_1w": "Normal(0, sigma) con sigma = EM 1W (%) si disponible; si no, RV20 semanal (%)"
    }
  },
  "liquidity": {
    "adv20_usd": 1622455261.08,
    "bid_ask": {
      "bid": 141.54,
      "ask": 141.89,
      "mid": 141.715,
      "spread_abs": 0.35,
      "spread_pct": 0.247
    }
  }
}