{
  "symbol": "NBIS",
  "latest_price": 233.38,
  "as_of": "2026-05-28T07:26:25.157872+00:00",
  "resistances": [
    {
      "type": "52_week_high",
      "level": 233.7299,
      "distance": 0.15,
      "strength_score": 9.0,
      "notes": "Primer test (pendiente) — señal débil (γ-$ bajo)",
      "meta": {
        "level_date": "2026-05-14",
        "atr10": 21.7819,
        "tolerance": 4.3564,
        "retests_since_origin": 0,
        "testing_now": false,
        "low_signal": true,
        "touch_prob_1w": {
          "sigma_pct": 15.38,
          "sigma_source": "em_pct_1w",
          "z": 0.01
        }
      },
      "prob_touch_1w_pct": 49.6,
      "unit": "pct"
    }
  ],
  "supports": [
    {
      "type": "52_week_low",
      "level": 34.72,
      "distance": 85.12,
      "strength_score": 8.5,
      "notes": "Re-test #3 (pendiente)",
      "meta": {
        "level_date": "2025-06-02",
        "atr10": 21.7819,
        "tolerance": 4.3564,
        "retests_since_origin": 2,
        "testing_now": false,
        "touch_prob_1w": {
          "sigma_pct": 15.38,
          "sigma_source": "em_pct_1w",
          "z": 5.534
        }
      },
      "prob_touch_1w_pct": 0.0,
      "unit": "pct"
    },
    {
      "type": "range_bottom_3_6m",
      "level": 83.53,
      "distance": 64.21,
      "strength_score": 9.0,
      "notes": "Suelo de rango 3–6m con 5 toques; último 2026-03-09 (pendiente)",
      "meta": {
        "first_touch_date": "2025-12-31",
        "last_touch_date": "2026-03-09",
        "touches": 5,
        "vol_factor_vs_median": 1.06,
        "tolerance": 4.3564,
        "testing_now": false,
        "touch_prob_1w": {
          "sigma_pct": 15.38,
          "sigma_source": "em_pct_1w",
          "z": 4.175
        }
      },
      "prob_touch_1w_pct": 0.0,
      "unit": "pct"
    },
    {
      "type": "gap_up_lower",
      "level": 66.64,
      "distance": 71.45,
      "strength_score": 8.2,
      "notes": "Gap alcista del 2025-09-09 (tam. 8.35%); abierto (pendiente)",
      "meta": {
        "gap_date": "2025-09-09",
        "gap_upper": 86.12,
        "gap_lower": 66.64,
        "gap_size": 19.48,
        "gap_size_pct_vs_price": 8.35,
        "vol_factor_vs_median": 6.37,
        "touches_since_gap": 0,
        "last_touch_date": null,
        "tolerance": 4.3564,
        "testing_now": false,
        "filled": false,
        "touch_prob_1w": {
          "sigma_pct": 15.38,
          "sigma_source": "em_pct_1w",
          "z": 4.646
        }
      },
      "prob_touch_1w_pct": 0.0,
      "unit": "pct"
    },
    {
      "type": "avwap_event_support",
      "level": 116.3847,
      "distance": 50.13,
      "strength_score": 9.2,
      "notes": "AVWAP anclado a gap-up del 2025-09-09 (pendiente)",
      "meta": {
        "anchor_type": "gap_up",
        "anchor_date": "2025-09-09",
        "vol_factor_vs_median": 6.37,
        "gap_size_atr": 0.89,
        "touches": null,
        "tolerance": 4.3564,
        "testing_now": false,
        "min_distance_pct": 0.05,
        "method": "daily_typical_price_vwap",
        "touch_prob_1w": {
          "sigma_pct": 15.38,
          "sigma_source": "em_pct_1w",
          "z": 3.259
        }
      },
      "prob_touch_1w_pct": 0.1,
      "unit": "pct"
    },
    {
      "type": "put_wall_gamma",
      "level": 210.0,
      "distance": 10.02,
      "unit": "pct",
      "strength_score": 9.3,
      "notes": "Put wall (γ-$) exp 2026-05-29; dominante (21.1% del lado put) — pendiente",
      "meta": {
        "expiration": "2026-05-29",
        "gamma_usd": 995.828,
        "gamma_usd_units": "millions",
        "gamma_usd_total_puts": 4726.612,
        "gamma_usd_share_pct": 21.1,
        "oi": 8364,
        "oi_share_pct": 6.9,
        "atr10": 21.7819,
        "tolerance": 4.3564,
        "window": "puts agregadas en top 3 expiraciones; sin filtro de distancia",
        "testing_now": false,
        "cluster": {
          "neighbors": [
            190.0,
            192.5,
            195.0,
            197.5,
            200.0,
            202.5,
            205.0,
            207.5,
            210.0,
            212.5,
            215.0,
            217.5,
            220.0,
            222.5,
            225.0,
            227.5,
            230.0
          ],
          "cluster_gamma_usd": 3004.211,
          "cluster_share_pct": 63.6
        },
        "method": "sum(|γ|·OI·spot²) por strike multi-exp (sin límites de distancia)",
        "touch_prob_1w": {
          "sigma_pct": 15.38,
          "sigma_source": "em_pct_1w",
          "z": 0.651
        }
      },
      "prob_touch_1w_pct": 25.7
    }
  ],
  "relative_strength": {
    "vs_spy": {
      "20d_diff_pct": 48.32,
      "60d_diff_pct": 119.62
    }
  },
  "call_walls_top": [
    {
      "level": 200.0,
      "expiration": "2026-05-29",
      "gamma_usd_millions": 451.093,
      "gamma_share_pct": 15.5,
      "oi": 4705,
      "oi_share_pct": 6.4,
      "cluster_neighbors": [
        180.0,
        182.5,
        185.0,
        187.5,
        190.0,
        192.5,
        195.0,
        197.5,
        200.0,
        202.5,
        205.0,
        207.5,
        210.0,
        212.5,
        215.0,
        217.5,
        220.0
      ],
      "cluster_gamma_usd": 1826.724,
      "cluster_share_pct": 62.6,
      "distance": -14.3
    },
    {
      "level": 220.0,
      "expiration": "2026-05-29",
      "gamma_usd_millions": 388.336,
      "gamma_share_pct": 13.3,
      "oi": 4404,
      "oi_share_pct": 6.0,
      "cluster_neighbors": [
        200.0,
        202.5,
        205.0,
        207.5,
        210.0,
        212.5,
        215.0,
        217.5,
        220.0,
        222.5,
        225.0,
        227.5,
        230.0,
        232.5,
        235.0,
        237.5,
        240.0
      ],
      "cluster_gamma_usd": 2164.559,
      "cluster_share_pct": 74.2,
      "distance": -5.73
    },
    {
      "level": 215.0,
      "expiration": "2026-06-05",
      "gamma_usd_millions": 252.941,
      "gamma_share_pct": 8.7,
      "oi": 3291,
      "oi_share_pct": 4.5,
      "cluster_neighbors": [
        195.0,
        197.5,
        200.0,
        202.5,
        205.0,
        207.5,
        210.0,
        212.5,
        215.0,
        217.5,
        220.0,
        222.5,
        225.0,
        227.5,
        230.0,
        232.5,
        235.0
      ],
      "cluster_gamma_usd": 2099.176,
      "cluster_share_pct": 71.9,
      "distance": -7.88
    },
    {
      "level": 235.0,
      "expiration": "2026-06-05",
      "gamma_usd_millions": 178.437,
      "gamma_share_pct": 6.1,
      "oi": 3508,
      "oi_share_pct": 4.8,
      "cluster_neighbors": [
        215.0,
        217.5,
        220.0,
        222.5,
        225.0,
        227.5,
        230.0,
        232.5,
        235.0,
        237.5,
        240.0,
        242.5,
        245.0,
        247.5,
        250.0,
        252.5,
        255.0
      ],
      "cluster_gamma_usd": 1615.791,
      "cluster_share_pct": 55.4,
      "distance": 0.69
    },
    {
      "level": 250.0,
      "expiration": "2026-05-29",
      "gamma_usd_millions": 176.05,
      "gamma_share_pct": 6.0,
      "oi": 6941,
      "oi_share_pct": 9.4,
      "cluster_neighbors": [
        230.0,
        232.5,
        235.0,
        237.5,
        240.0,
        242.5,
        245.0,
        247.5,
        250.0,
        252.5,
        255.0,
        257.5,
        260.0,
        262.5,
        265.0,
        267.5,
        270.0
      ],
      "cluster_gamma_usd": 795.859,
      "cluster_share_pct": 27.3,
      "distance": 7.12
    }
  ],
  "put_walls_top": [
    {
      "level": 210.0,
      "expiration": "2026-05-29",
      "gamma_usd_millions": 995.828,
      "gamma_share_pct": 21.1,
      "oi": 8364,
      "oi_share_pct": 6.9,
      "cluster_neighbors": [
        190.0,
        192.5,
        195.0,
        197.5,
        200.0,
        202.5,
        205.0,
        207.5,
        210.0,
        212.5,
        215.0,
        217.5,
        220.0,
        222.5,
        225.0,
        227.5,
        230.0
      ],
      "cluster_gamma_usd": 3004.211,
      "cluster_share_pct": 63.6,
      "distance": -10.02
    },
    {
      "level": 187.5,
      "expiration": "2026-05-29",
      "gamma_usd_millions": 418.947,
      "gamma_share_pct": 8.9,
      "oi": 7789,
      "oi_share_pct": 6.5,
      "cluster_neighbors": [
        167.5,
        170.0,
        172.5,
        175.0,
        177.5,
        180.0,
        182.5,
        185.0,
        187.5,
        190.0,
        192.5,
        195.0,
        197.5,
        200.0,
        202.5,
        205.0,
        207.5
      ],
      "cluster_gamma_usd": 2802.67,
      "cluster_share_pct": 59.3,
      "distance": -19.66
    },
    {
      "level": 195.0,
      "expiration": "2026-05-29",
      "gamma_usd_millions": 409.373,
      "gamma_share_pct": 8.7,
      "oi": 5284,
      "oi_share_pct": 4.4,
      "cluster_neighbors": [
        175.0,
        177.5,
        180.0,
        182.5,
        185.0,
        187.5,
        190.0,
        192.5,
        195.0,
        197.5,
        200.0,
        202.5,
        205.0,
        207.5,
        210.0,
        212.5,
        215.0
      ],
      "cluster_gamma_usd": 3920.889,
      "cluster_share_pct": 83.0,
      "distance": -16.45
    },
    {
      "level": 200.0,
      "expiration": "2026-05-29",
      "gamma_usd_millions": 405.928,
      "gamma_share_pct": 8.6,
      "oi": 4656,
      "oi_share_pct": 3.9,
      "cluster_neighbors": [
        180.0,
        182.5,
        185.0,
        187.5,
        190.0,
        192.5,
        195.0,
        197.5,
        200.0,
        202.5,
        205.0,
        207.5,
        210.0,
        212.5,
        215.0,
        217.5,
        220.0
      ],
      "cluster_gamma_usd": 3827.481,
      "cluster_share_pct": 81.0,
      "distance": -14.3
    },
    {
      "level": 185.0,
      "expiration": "2026-05-29",
      "gamma_usd_millions": 400.073,
      "gamma_share_pct": 8.5,
      "oi": 8985,
      "oi_share_pct": 7.4,
      "cluster_neighbors": [
        165.0,
        167.5,
        170.0,
        172.5,
        175.0,
        177.5,
        180.0,
        182.5,
        185.0,
        187.5,
        190.0,
        192.5,
        195.0,
        197.5,
        200.0,
        202.5,
        205.0
      ],
      "cluster_gamma_usd": 2755.732,
      "cluster_share_pct": 58.3,
      "distance": -20.73
    }
  ],
  "technicals": {
    "rsi14": 54.56,
    "sma": {
      "20": 189.8635,
      "50": 154.5516,
      "200": 111.0293
    },
    "bollinger20_2": {
      "upper": 237.9443,
      "middle": 189.8635,
      "lower": 141.7827,
      "width_pct": 50.65,
      "method": "SMA20 ± 2·σ(cierre)"
    },
    "keltner_ema20_atr10": {
      "upper": 235.0556,
      "center": 191.4917,
      "lower": 147.9278,
      "mult": 2.0,
      "method": "EMA20(typical) ± mult·ATR10"
    },
    "donchian20": {
      "high": 233.7299,
      "low": 134.22
    },
    "atr10": 21.7819,
    "volume": {
      "avg_20d": 17929453.25,
      "median_20d": 15408645.5,
      "avg_dollar_20d": 3469196976.82,
      "last_complete_day": {
        "date": "2026-05-27",
        "shares": 13981092,
        "rel_to_20d": 0.78
      },
      "series": {
        "shares_20d": [
          14962744,
          12682921,
          15854547,
          24793296,
          11763239,
          19331135,
          19203362,
          12929585,
          14061617,
          11723224,
          38769974,
          29737783,
          22919763,
          21056547,
          16832930,
          13063993,
          23027656,
          10606677,
          11286980,
          13981092
        ],
        "dollar_volume_20d": [
          2112589825.36,
          1753160169.83,
          2449368966.03,
          4374033280.32,
          2069389004.88,
          3771311127.15,
          3548205196.74,
          2289183024.25,
          2616866923.7,
          2099746650.64,
          8035852510.98,
          6576510710.45,
          5040972674.22,
          4208361483.42,
          3328375248.9,
          2505935137.26,
          5064472384.08,
          2277996019.29,
          2348369058.8,
          2913240140.04
        ]
      },
      "current_session": {
        "shares": 0.0,
        "comparable_to_avg_20d": false
      },
      "note": "ratios calculados contra último día COMPLETO; intradía solo informativo"
    },
    "trend": {
      "above_sma200": true,
      "price_vs_sma": {
        "20": 9.75,
        "50": 34.82,
        "200": 87.67
      },
      "price_20d_change_pct": 53.77,
      "price_50d_change_pct": 60.47,
      "bollinger_pos_pct": 69.2
    }
  },
  "options": {
    "expected_move_1w": {
      "target": "1w",
      "expiration": "2026-06-05",
      "source_expiration": "2026-06-05",
      "dte": 8,
      "weeklyized": false,
      "dollars": 35.9,
      "percent": 15.38,
      "method": "ATM straddle mid (~1W)"
    },
    "max_pain": {
      "expiration": "2026-06-05",
      "strike": 195.0
    },
    "dealer_gamma": {
      "gex_total_usd_millions": -1807.507,
      "gamma_regime": "negative",
      "method": "sum_calls_minus_puts"
    },
    "summary_by_expiration": [
      {
        "date": "2026-05-29",
        "dte": 1,
        "atm_iv": 2.6621,
        "expected_move": {
          "dollars": 26.015,
          "percent": 0.1115,
          "method": "ATM straddle mid"
        },
        "total_call_oi": 52018,
        "total_put_oi": 109654,
        "put_call_oi_ratio": 2.108
      },
      {
        "date": "2026-06-05",
        "dte": 8,
        "atm_iv": 1.2988,
        "expected_move": {
          "dollars": 35.9,
          "percent": 0.1538,
          "method": "ATM straddle mid"
        },
        "total_call_oi": 17860,
        "total_put_oi": 22769,
        "put_call_oi_ratio": 1.275
      },
      {
        "date": "2026-06-12",
        "dte": 15,
        "atm_iv": 1.1599,
        "expected_move": {
          "dollars": 43.9,
          "percent": 0.1881,
          "method": "ATM straddle mid"
        },
        "total_call_oi": 6049,
        "total_put_oi": 10887,
        "put_call_oi_ratio": 1.8
      }
    ],
    "max_pain_by_expiration": [
      {
        "date": "2026-05-29",
        "strike": 210.0,
        "confidence": 0.0
      },
      {
        "date": "2026-06-05",
        "strike": 195.0,
        "confidence": 0.0
      },
      {
        "date": "2026-06-12",
        "strike": 202.5,
        "confidence": 0.0
      }
    ]
  },
  "options_overview": {
    "put_call_oi_ratio": {
      "near_term": {
        "scope": "near_term",
        "expirations_considered": [
          "2026-05-29",
          "2026-06-05",
          "2026-06-12"
        ],
        "total_put_oi": 143310,
        "total_call_oi": 75927,
        "ratio": 1.887,
        "dte_buckets": {
          "0_7": {
            "puts": 109654,
            "calls": 52018,
            "ratio": 2.108,
            "expirations": [
              "2026-05-29"
            ]
          },
          "8_30": {
            "puts": 33656,
            "calls": 23909,
            "ratio": 1.408,
            "expirations": [
              "2026-06-05",
              "2026-06-12"
            ]
          },
          "31_60": {
            "puts": 0,
            "calls": 0,
            "ratio": null,
            "expirations": []
          },
          "61_plus": {
            "puts": 0,
            "calls": 0,
            "ratio": null,
            "expirations": []
          }
        },
        "per_expiration": [
          {
            "expiration": "2026-05-29",
            "dte": 1,
            "puts": 109654,
            "calls": 52018,
            "ratio": 2.108
          },
          {
            "expiration": "2026-06-05",
            "dte": 8,
            "puts": 22769,
            "calls": 17860,
            "ratio": 1.275
          },
          {
            "expiration": "2026-06-12",
            "dte": 15,
            "puts": 10887,
            "calls": 6049,
            "ratio": 1.8
          }
        ]
      },
      "thru_60d": {
        "scope": "thru_60d",
        "expirations_considered": [
          "2026-05-29",
          "2026-06-05",
          "2026-06-12",
          "2026-06-18",
          "2026-06-26",
          "2026-07-02",
          "2026-07-17"
        ],
        "total_put_oi": 254205,
        "total_call_oi": 179382,
        "ratio": 1.417,
        "dte_buckets": {
          "0_7": {
            "puts": 109654,
            "calls": 52018,
            "ratio": 2.108,
            "expirations": [
              "2026-05-29"
            ]
          },
          "8_30": {
            "puts": 122680,
            "calls": 103518,
            "ratio": 1.185,
            "expirations": [
              "2026-06-05",
              "2026-06-12",
              "2026-06-18",
              "2026-06-26"
            ]
          },
          "31_60": {
            "puts": 21871,
            "calls": 23846,
            "ratio": 0.917,
            "expirations": [
              "2026-07-02",
              "2026-07-17"
            ]
          },
          "61_plus": {
            "puts": 0,
            "calls": 0,
            "ratio": null,
            "expirations": []
          }
        },
        "per_expiration": [
          {
            "expiration": "2026-05-29",
            "dte": 1,
            "puts": 109654,
            "calls": 52018,
            "ratio": 2.108
          },
          {
            "expiration": "2026-06-05",
            "dte": 8,
            "puts": 22769,
            "calls": 17860,
            "ratio": 1.275
          },
          {
            "expiration": "2026-06-12",
            "dte": 15,
            "puts": 10887,
            "calls": 6049,
            "ratio": 1.8
          },
          {
            "expiration": "2026-06-18",
            "dte": 21,
            "puts": 82632,
            "calls": 74567,
            "ratio": 1.108
          },
          {
            "expiration": "2026-06-26",
            "dte": 29,
            "puts": 6392,
            "calls": 5042,
            "ratio": 1.268
          },
          {
            "expiration": "2026-07-02",
            "dte": 35,
            "puts": 2460,
            "calls": 830,
            "ratio": 2.964
          },
          {
            "expiration": "2026-07-17",
            "dte": 50,
            "puts": 19411,
            "calls": 23016,
            "ratio": 0.843
          }
        ]
      },
      "default_scope": "near_term",
      "ratio": 1.887,
      "total_put_oi": 143310,
      "total_call_oi": 75927
    }
  },
  "vols": {
    "rv20_annual_pct": 111.307,
    "rv60_annual_pct": 103.459,
    "rv20_weekly_pct": 15.436,
    "rv60_weekly_pct": 14.347,
    "em_pct_1w": 15.38,
    "em_abs_1w": 35.9,
    "iv_to_rv_ratio": 0.996,
    "em_to_atr_ratio": 1.648,
    "windows": {
      "rv": [
        20,
        60
      ]
    },
    "units": {
      "rv_annual_pct": "percent",
      "rv_weekly_pct": "percent",
      "em_pct_1w": "percent",
      "em_abs_1w": "dollars"
    },
    "method": "std(log_returns_daily) * sqrt(252); weekly = annual/sqrt(52)",
    "em_basis": {
      "source_expiration": "2026-06-05",
      "dte": 8,
      "weeklyized_from_dte": false
    }
  },
  "forward_returns": {
    "lookback_days": 252,
    "series": {
      "anchor_dates": [
        "2025-05-23",
        "2025-05-27",
        "2025-05-28",
        "2025-05-29",
        "2025-05-30",
        "2025-06-02",
        "2025-06-03",
        "2025-06-04",
        "2025-06-05",
        "2025-06-06",
        "2025-06-09",
        "2025-06-10",
        "2025-06-11",
        "2025-06-12",
        "2025-06-13",
        "2025-06-16",
        "2025-06-17",
        "2025-06-18",
        "2025-06-20",
        "2025-06-23",
        "2025-06-24",
        "2025-06-25",
        "2025-06-26",
        "2025-06-27",
        "2025-06-30",
        "2025-07-01",
        "2025-07-02",
        "2025-07-03",
        "2025-07-07",
        "2025-07-08",
        "2025-07-09",
        "2025-07-10",
        "2025-07-11",
        "2025-07-14",
        "2025-07-15",
        "2025-07-16",
        "2025-07-17",
        "2025-07-18",
        "2025-07-21",
        "2025-07-22",
        "2025-07-23",
        "2025-07-24",
        "2025-07-25",
        "2025-07-28",
        "2025-07-29",
        "2025-07-30",
        "2025-07-31",
        "2025-08-01",
        "2025-08-04",
        "2025-08-05",
        "2025-08-06",
        "2025-08-07",
        "2025-08-08",
        "2025-08-11",
        "2025-08-12",
        "2025-08-13",
        "2025-08-14",
        "2025-08-15",
        "2025-08-18",
        "2025-08-19",
        "2025-08-20",
        "2025-08-21",
        "2025-08-22",
        "2025-08-25",
        "2025-08-26",
        "2025-08-27",
        "2025-08-28",
        "2025-08-29",
        "2025-09-02",
        "2025-09-03",
        "2025-09-04",
        "2025-09-05",
        "2025-09-08",
        "2025-09-09",
        "2025-09-10",
        "2025-09-11",
        "2025-09-12",
        "2025-09-15",
        "2025-09-16",
        "2025-09-17",
        "2025-09-18",
        "2025-09-19",
        "2025-09-22",
        "2025-09-23",
        "2025-09-24",
        "2025-09-25",
        "2025-09-26",
        "2025-09-29",
        "2025-09-30",
        "2025-10-01",
        "2025-10-02",
        "2025-10-03",
        "2025-10-06",
        "2025-10-07",
        "2025-10-08",
        "2025-10-09",
        "2025-10-10",
        "2025-10-13",
        "2025-10-14",
        "2025-10-15",
        "2025-10-16",
        "2025-10-17",
        "2025-10-20",
        "2025-10-21",
        "2025-10-22",
        "2025-10-23",
        "2025-10-24",
        "2025-10-27",
        "2025-10-28",
        "2025-10-29",
        "2025-10-30",
        "2025-10-31",
        "2025-11-03",
        "2025-11-04",
        "2025-11-05",
        "2025-11-06",
        "2025-11-07",
        "2025-11-10",
        "2025-11-11",
        "2025-11-12",
        "2025-11-13",
        "2025-11-14",
        "2025-11-17",
        "2025-11-18",
        "2025-11-19",
        "2025-11-20",
        "2025-11-21",
        "2025-11-24",
        "2025-11-25",
        "2025-11-26",
        "2025-11-28",
        "2025-12-01",
        "2025-12-02",
        "2025-12-03",
        "2025-12-04",
        "2025-12-05",
        "2025-12-08",
        "2025-12-09",
        "2025-12-10",
        "2025-12-11",
        "2025-12-12",
        "2025-12-15",
        "2025-12-16",
        "2025-12-17",
        "2025-12-18",
        "2025-12-19",
        "2025-12-22",
        "2025-12-23",
        "2025-12-24",
        "2025-12-26",
        "2025-12-29",
        "2025-12-30",
        "2025-12-31",
        "2026-01-02",
        "2026-01-05",
        "2026-01-06",
        "2026-01-07",
        "2026-01-08",
        "2026-01-09",
        "2026-01-12",
        "2026-01-13",
        "2026-01-14",
        "2026-01-15",
        "2026-01-16",
        "2026-01-20",
        "2026-01-21",
        "2026-01-22",
        "2026-01-23",
        "2026-01-26",
        "2026-01-27",
        "2026-01-28",
        "2026-01-29",
        "2026-01-30",
        "2026-02-02",
        "2026-02-03",
        "2026-02-04",
        "2026-02-05",
        "2026-02-06",
        "2026-02-09",
        "2026-02-10",
        "2026-02-11",
        "2026-02-12",
        "2026-02-13",
        "2026-02-17",
        "2026-02-18",
        "2026-02-19",
        "2026-02-20",
        "2026-02-23",
        "2026-02-24",
        "2026-02-25",
        "2026-02-26",
        "2026-02-27",
        "2026-03-02",
        "2026-03-03",
        "2026-03-04",
        "2026-03-05",
        "2026-03-06",
        "2026-03-09",
        "2026-03-10",
        "2026-03-11",
        "2026-03-12",
        "2026-03-13",
        "2026-03-16",
        "2026-03-17",
        "2026-03-18",
        "2026-03-19",
        "2026-03-20",
        "2026-03-23",
        "2026-03-24",
        "2026-03-25",
        "2026-03-26",
        "2026-03-27",
        "2026-03-30",
        "2026-03-31",
        "2026-04-01",
        "2026-04-02",
        "2026-04-06",
        "2026-04-07",
        "2026-04-08",
        "2026-04-09",
        "2026-04-10",
        "2026-04-13",
        "2026-04-14",
        "2026-04-15",
        "2026-04-16",
        "2026-04-17",
        "2026-04-20",
        "2026-04-21",
        "2026-04-22",
        "2026-04-23",
        "2026-04-24",
        "2026-04-27",
        "2026-04-28",
        "2026-04-29",
        "2026-04-30",
        "2026-05-01",
        "2026-05-04",
        "2026-05-05",
        "2026-05-06",
        "2026-05-07",
        "2026-05-08",
        "2026-05-11",
        "2026-05-12",
        "2026-05-13",
        "2026-05-14",
        "2026-05-15",
        "2026-05-18",
        "2026-05-19",
        "2026-05-20",
        "2026-05-21",
        "2026-05-22",
        "2026-05-26"
      ],
      "t1_dates": [
        "2025-05-27",
        "2025-05-28",
        "2025-05-29",
        "2025-05-30",
        "2025-06-02",
        "2025-06-03",
        "2025-06-04",
        "2025-06-05",
        "2025-06-06",
        "2025-06-09",
        "2025-06-10",
        "2025-06-11",
        "2025-06-12",
        "2025-06-13",
        "2025-06-16",
        "2025-06-17",
        "2025-06-18",
        "2025-06-20",
        "2025-06-23",
        "2025-06-24",
        "2025-06-25",
        "2025-06-26",
        "2025-06-27",
        "2025-06-30",
        "2025-07-01",
        "2025-07-02",
        "2025-07-03",
        "2025-07-07",
        "2025-07-08",
        "2025-07-09",
        "2025-07-10",
        "2025-07-11",
        "2025-07-14",
        "2025-07-15",
        "2025-07-16",
        "2025-07-17",
        "2025-07-18",
        "2025-07-21",
        "2025-07-22",
        "2025-07-23",
        "2025-07-24",
        "2025-07-25",
        "2025-07-28",
        "2025-07-29",
        "2025-07-30",
        "2025-07-31",
        "2025-08-01",
        "2025-08-04",
        "2025-08-05",
        "2025-08-06",
        "2025-08-07",
        "2025-08-08",
        "2025-08-11",
        "2025-08-12",
        "2025-08-13",
        "2025-08-14",
        "2025-08-15",
        "2025-08-18",
        "2025-08-19",
        "2025-08-20",
        "2025-08-21",
        "2025-08-22",
        "2025-08-25",
        "2025-08-26",
        "2025-08-27",
        "2025-08-28",
        "2025-08-29",
        "2025-09-02",
        "2025-09-03",
        "2025-09-04",
        "2025-09-05",
        "2025-09-08",
        "2025-09-09",
        "2025-09-10",
        "2025-09-11",
        "2025-09-12",
        "2025-09-15",
        "2025-09-16",
        "2025-09-17",
        "2025-09-18",
        "2025-09-19",
        "2025-09-22",
        "2025-09-23",
        "2025-09-24",
        "2025-09-25",
        "2025-09-26",
        "2025-09-29",
        "2025-09-30",
        "2025-10-01",
        "2025-10-02",
        "2025-10-03",
        "2025-10-06",
        "2025-10-07",
        "2025-10-08",
        "2025-10-09",
        "2025-10-10",
        "2025-10-13",
        "2025-10-14",
        "2025-10-15",
        "2025-10-16",
        "2025-10-17",
        "2025-10-20",
        "2025-10-21",
        "2025-10-22",
        "2025-10-23",
        "2025-10-24",
        "2025-10-27",
        "2025-10-28",
        "2025-10-29",
        "2025-10-30",
        "2025-10-31",
        "2025-11-03",
        "2025-11-04",
        "2025-11-05",
        "2025-11-06",
        "2025-11-07",
        "2025-11-10",
        "2025-11-11",
        "2025-11-12",
        "2025-11-13",
        "2025-11-14",
        "2025-11-17",
        "2025-11-18",
        "2025-11-19",
        "2025-11-20",
        "2025-11-21",
        "2025-11-24",
        "2025-11-25",
        "2025-11-26",
        "2025-11-28",
        "2025-12-01",
        "2025-12-02",
        "2025-12-03",
        "2025-12-04",
        "2025-12-05",
        "2025-12-08",
        "2025-12-09",
        "2025-12-10",
        "2025-12-11",
        "2025-12-12",
        "2025-12-15",
        "2025-12-16",
        "2025-12-17",
        "2025-12-18",
        "2025-12-19",
        "2025-12-22",
        "2025-12-23",
        "2025-12-24",
        "2025-12-26",
        "2025-12-29",
        "2025-12-30",
        "2025-12-31",
        "2026-01-02",
        "2026-01-05",
        "2026-01-06",
        "2026-01-07",
        "2026-01-08",
        "2026-01-09",
        "2026-01-12",
        "2026-01-13",
        "2026-01-14",
        "2026-01-15",
        "2026-01-16",
        "2026-01-20",
        "2026-01-21",
        "2026-01-22",
        "2026-01-23",
        "2026-01-26",
        "2026-01-27",
        "2026-01-28",
        "2026-01-29",
        "2026-01-30",
        "2026-02-02",
        "2026-02-03",
        "2026-02-04",
        "2026-02-05",
        "2026-02-06",
        "2026-02-09",
        "2026-02-10",
        "2026-02-11",
        "2026-02-12",
        "2026-02-13",
        "2026-02-17",
        "2026-02-18",
        "2026-02-19",
        "2026-02-20",
        "2026-02-23",
        "2026-02-24",
        "2026-02-25",
        "2026-02-26",
        "2026-02-27",
        "2026-03-02",
        "2026-03-03",
        "2026-03-04",
        "2026-03-05",
        "2026-03-06",
        "2026-03-09",
        "2026-03-10",
        "2026-03-11",
        "2026-03-12",
        "2026-03-13",
        "2026-03-16",
        "2026-03-17",
        "2026-03-18",
        "2026-03-19",
        "2026-03-20",
        "2026-03-23",
        "2026-03-24",
        "2026-03-25",
        "2026-03-26",
        "2026-03-27",
        "2026-03-30",
        "2026-03-31",
        "2026-04-01",
        "2026-04-02",
        "2026-04-06",
        "2026-04-07",
        "2026-04-08",
        "2026-04-09",
        "2026-04-10",
        "2026-04-13",
        "2026-04-14",
        "2026-04-15",
        "2026-04-16",
        "2026-04-17",
        "2026-04-20",
        "2026-04-21",
        "2026-04-22",
        "2026-04-23",
        "2026-04-24",
        "2026-04-27",
        "2026-04-28",
        "2026-04-29",
        "2026-04-30",
        "2026-05-01",
        "2026-05-04",
        "2026-05-05",
        "2026-05-06",
        "2026-05-07",
        "2026-05-08",
        "2026-05-11",
        "2026-05-12",
        "2026-05-13",
        "2026-05-14",
        "2026-05-15",
        "2026-05-18",
        "2026-05-19",
        "2026-05-20",
        "2026-05-21",
        "2026-05-22",
        "2026-05-26",
        "2026-05-27"
      ],
      "t1_close_from_close_pct": [
        3.187,
        -0.552,
        -3.939,
        -3.391,
        -1.986,
        3.47,
        5.688,
        17.543,
        4.276,
        8.906,
        -0.133,
        -3.695,
        -0.573,
        -6.265,
        7.066,
        -4.221,
        -0.021,
        -0.724,
        -1.021,
        7.456,
        -4.9,
        8.409,
        -1.445,
        6.732,
        -9.073,
        -0.676,
        0.56,
        -4.796,
        -1.547,
        -2.229,
        0.825,
        -4.588,
        17.269,
        3.041,
        -0.411,
        0.713,
        -1.676,
        -0.796,
        -2.597,
        1.706,
        0.54,
        -1.515,
        2.686,
        -4.455,
        1.766,
        6.122,
        -4.464,
        4.173,
        1.846,
        -0.145,
        18.551,
        5.313,
        2.123,
        7.247,
        -6.239,
        -3.072,
        4.616,
        1.285,
        -7.375,
        0.417,
        -1.912,
        4.231,
        1.508,
        0.657,
        -0.539,
        2.767,
        -5.164,
        -3.806,
        -0.107,
        -1.127,
        0.863,
        -2.154,
        49.422,
        -2.434,
        -4.497,
        1.368,
        0.608,
        -1.682,
        5.2,
        0.043,
        5.514,
        7.341,
        1.126,
        5.037,
        -4.672,
        -0.222,
        2.34,
        1.86,
        2.975,
        8.875,
        1.676,
        -2.375,
        -5.795,
        3.653,
        8.721,
        -2.307,
        4.538,
        -5.396,
        -1.81,
        -2.217,
        -7.802,
        -3.914,
        -4.33,
        -5.428,
        7.646,
        10.456,
        6.967,
        -2.87,
        2.684,
        -0.735,
        5.347,
        -7.912,
        -8.243,
        5.844,
        -6.462,
        1.681,
        -1.195,
        -7.03,
        -7.689,
        -6.072,
        -5.743,
        2.921,
        5.304,
        5.003,
        -10.971,
        -1.63,
        10.377,
        -3.286,
        6.537,
        0.19,
        5.566,
        -3.694,
        2.561,
        3.922,
        -4.63,
        2.336,
        -3.907,
        -2.925,
        0.737,
        -6.99,
        -7.469,
        -0.234,
        -6.794,
        3.499,
        14.56,
        4.214,
        -3.432,
        1.222,
        -3.885,
        -1.77,
        -1.011,
        -1.72,
        7.461,
        3.202,
        7.982,
        -4.02,
        1.133,
        0.647,
        9.599,
        -1.77,
        -3.272,
        1.868,
        4.664,
        -8.682,
        -0.423,
        -2.043,
        -2.426,
        -3.217,
        7.009,
        2.616,
        -5.496,
        -10.241,
        3.486,
        2.03,
        -8.405,
        -10.341,
        16.556,
        7.875,
        -1.174,
        -3.464,
        1.264,
        9.228,
        -0.5,
        4.389,
        5.707,
        -9.005,
        2.747,
        1.958,
        3.451,
        -1.168,
        -13.053,
        -0.197,
        -4.626,
        12.65,
        -2.178,
        -6.607,
        6.28,
        1.569,
        16.141,
        -3.531,
        4.545,
        14.962,
        -10.412,
        1.917,
        2.497,
        -3.209,
        -2.95,
        0.666,
        0.157,
        -7.924,
        -4.86,
        -8.49,
        12.465,
        -1.744,
        6.739,
        3.418,
        4.318,
        6.474,
        9.064,
        6.338,
        6.615,
        4.775,
        2.983,
        -0.857,
        -4.959,
        1.285,
        -1.64,
        -0.262,
        0.602,
        -6.315,
        -1.495,
        -6.519,
        4.192,
        -2.096,
        11.763,
        14.195,
        -0.283,
        10.897,
        -5.29,
        -4.178,
        5.112,
        -3.756,
        15.722,
        6.697,
        -0.547,
        -9.13,
        -1.066,
        -2.989,
        14.654,
        -2.346,
        -3.124,
        0.149
      ],
      "t1_high_from_close_pct": [
        3.887,
        2.712,
        5.556,
        0.368,
        -1.932,
        5.441,
        8.398,
        26.25,
        4.903,
        14.002,
        0.019,
        1.428,
        2.768,
        -1.094,
        9.951,
        -0.793,
        4.18,
        2.939,
        0.688,
        11.626,
        6.997,
        9.563,
        1.559,
        7.542,
        0.09,
        1.769,
        2.041,
        -1.821,
        1.484,
        3.609,
        2.573,
        2.531,
        17.856,
        6.699,
        0.224,
        5.346,
        2.067,
        10.181,
        -0.134,
        2.019,
        3.662,
        1.15,
        2.793,
        3.697,
        4.167,
        11.386,
        -1.286,
        4.865,
        4.209,
        1.305,
        28.045,
        9.463,
        10.439,
        8.085,
        -0.159,
        1.26,
        5.127,
        1.354,
        -1.089,
        0.461,
        1.171,
        5.289,
        2.551,
        3.97,
        1.87,
        4.85,
        -0.486,
        -0.645,
        1.948,
        1.295,
        3.821,
        1.787,
        54.043,
        5.004,
        0.514,
        3.151,
        4.435,
        0.374,
        6.228,
        3.827,
        5.769,
        9.334,
        3.171,
        6.54,
        0.751,
        1.899,
        4.475,
        6.741,
        3.215,
        9.627,
        5.648,
        6.079,
        2.673,
        6.466,
        9.279,
        6.378,
        6.907,
        -1.237,
        2.996,
        4.085,
        -2.005,
        3.553,
        -0.752,
        3.376,
        8.112,
        10.635,
        7.88,
        2.87,
        3.382,
        2.67,
        6.418,
        3.142,
        -3.063,
        6.939,
        3.419,
        1.7,
        6.371,
        4.193,
        3.355,
        -3.052,
        0.417,
        7.314,
        8.967,
        6.826,
        8.015,
        4.844,
        11.698,
        -0.675,
        7.599,
        2.524,
        7.094,
        2.796,
        2.706,
        4.974,
        -1.411,
        2.509,
        0.551,
        0.705,
        1.987,
        1.453,
        0.627,
        0.518,
        4.138,
        6.494,
        15.943,
        7.199,
        -0.279,
        1.544,
        0.538,
        1.165,
        1.069,
        1.526,
        8.428,
        6.103,
        8.456,
        2.105,
        6.579,
        7.883,
        10.977,
        0.578,
        1.204,
        6.031,
        6.368,
        -3.918,
        3.132,
        5.168,
        2.102,
        6.751,
        8.834,
        4.067,
        -1.175,
        -3.024,
        4.766,
        3.664,
        -2.54,
        -1.906,
        17.314,
        8.804,
        2.877,
        3.225,
        2.426,
        11.802,
        1.306,
        7.055,
        6.071,
        0.66,
        3.312,
        3.121,
        4.738,
        2.073,
        -5.32,
        0.216,
        -1.253,
        13.456,
        1.503,
        -0.732,
        6.571,
        3.644,
        18.303,
        -0.853,
        7.895,
        17.131,
        -6.431,
        5.539,
        2.733,
        1.813,
        3.137,
        3.198,
        3.385,
        -1.555,
        0.274,
        1.408,
        12.606,
        3.961,
        6.876,
        4.613,
        4.763,
        8.816,
        9.24,
        9.895,
        10.023,
        7.466,
        3.007,
        1.163,
        -0.774,
        2.934,
        2.57,
        6.95,
        6.193,
        5.201,
        1.114,
        -2.414,
        6.044,
        4.101,
        12.855,
        16.124,
        2.007,
        11.409,
        1.435,
        1.883,
        10.961,
        -0.263,
        21.344,
        12.766,
        3.455,
        -0.85,
        1.476,
        3.297,
        18.241,
        0.905,
        2.905,
        0.759
      ],
      "t1_close_from_open_pct": [
        0.632,
        -1.37,
        -7.782,
        -1.922,
        3.431,
        1.664,
        3.836,
        11.782,
        4.288,
        4.606,
        2.961,
        -3.713,
        0.03,
        -3.104,
        5.125,
        -3.049,
        -0.627,
        -1.418,
        1.021,
        4.122,
        -8.925,
        6.113,
        -2.207,
        3.731,
        -7.857,
        -0.567,
        -1.451,
        -3.011,
        -2.079,
        -2.848,
        -0.151,
        -4.762,
        6.172,
        2.303,
        -0.504,
        -0.223,
        -3.403,
        -2.495,
        -2.186,
        1.328,
        -2.102,
        -2.19,
        2.051,
        -5.423,
        0.806,
        2.063,
        0.058,
        2.227,
        -1.209,
        -1.431,
        1.46,
        0.887,
        0.486,
        2.594,
        -5.927,
        -1.849,
        4.861,
        1.54,
        -6.355,
        3.505,
        -3.047,
        5.297,
        0.806,
        0.27,
        -1.958,
        1.565,
        -4.508,
        -0.273,
        -1.839,
        -0.817,
        -1.549,
        -0.943,
        -1.523,
        1.91,
        -3.755,
        -0.855,
        -1.782,
        -1.941,
        2.629,
        -1.004,
        5.492,
        4.561,
        -0.222,
        3.752,
        -0.106,
        -2.029,
        0.768,
        -1.036,
        3.487,
        1.697,
        0.586,
        -5.634,
        -7.921,
        0.66,
        9.638,
        -3.979,
        0.185,
        -2.917,
        -4.602,
        -3.943,
        -3.913,
        -6.67,
        -3.337,
        -7.551,
        5.811,
        5.488,
        3.738,
        -3.642,
        0.66,
        2.459,
        3.301,
        -10.097,
        -1.615,
        2.957,
        -8.457,
        6.488,
        -4.541,
        -10.435,
        -9.443,
        -2.487,
        1.433,
        2.577,
        8.069,
        2.22,
        -14.875,
        -2.677,
        6.575,
        -0.459,
        0.895,
        -1.74,
        9.513,
        -3.896,
        4.104,
        3.765,
        -2.292,
        3.125,
        -1.713,
        -2.235,
        5.695,
        -6.023,
        -7.9,
        1.728,
        -10.275,
        -1.214,
        10.924,
        0.28,
        -0.31,
        0.997,
        -4.284,
        1.883,
        -1.395,
        -1.95,
        3.409,
        -2.284,
        4.728,
        -2.828,
        0.527,
        -0.976,
        9.164,
        -1.77,
        -3.592,
        -0.641,
        2.58,
        -2.494,
        -2.196,
        -5.058,
        -2.275,
        -6.396,
        3.731,
        0.43,
        -3.508,
        -6.948,
        2.739,
        0.022,
        -5.299,
        -6.659,
        8.678,
        9.982,
        -1.211,
        -4.633,
        6.694,
        9.07,
        1.583,
        2.076,
        7.149,
        -8.135,
        4.47,
        3.236,
        1.076,
        -1.057,
        -7.609,
        3.42,
        0.754,
        8.164,
        -1.137,
        -3.218,
        8.677,
        1.356,
        6.5,
        -0.963,
        2.273,
        4.088,
        -3.332,
        3.275,
        5.436,
        -2.37,
        -2.193,
        -1.089,
        -1.523,
        -6.432,
        -4.734,
        -9.761,
        5.899,
        -3.771,
        12.872,
        3.571,
        6.124,
        -1.482,
        9.064,
        7.477,
        8.311,
        0.521,
        4.084,
        -0.994,
        -4.054,
        1.376,
        -2.897,
        -4.126,
        0.757,
        -10.087,
        -2.311,
        -2.088,
        0.782,
        -4.79,
        9.312,
        9.998,
        2.488,
        8.628,
        -2.758,
        -3.62,
        3.446,
        -0.726,
        1.68,
        3.644,
        1.071,
        -8.098,
        3.524,
        -5.957,
        3.868,
        -2.048,
        -5.717,
        0.282
      ]
    },
    "stats": {
      "close_from_close": {
        "count": 252,
        "mean": 0.87,
        "median": -0.064,
        "up_rate_pct": 49.6,
        "p05": -7.917,
        "p95": 12.079
      },
      "high_from_close": {
        "count": 252,
        "mean": 4.577,
        "median": 3.365,
        "up_rate_pct": 86.9,
        "p05": -1.476,
        "p95": 13.126
      },
      "close_from_open": {
        "count": 252,
        "mean": -0.023,
        "median": -0.292,
        "up_rate_pct": 48.02,
        "p05": -7.876,
        "p95": 8.65
      }
    },
    "latest": {
      "anchor_date": "2026-05-26",
      "t1_date": "2026-05-27",
      "close_from_close_pct": 0.149,
      "high_from_close_pct": 0.759,
      "close_from_open_pct": 0.282
    }
  },
  "conventions": {
    "returns": {
      "basis": "close_to_close",
      "intraday_high_basis": "close_to_high",
      "t_is_trading_days": true
    },
    "probabilities": {
      "touch_1w": "Normal(0, sigma) con sigma = EM 1W (%) si disponible; si no, RV20 semanal (%)"
    }
  },
  "trend_1_2w": {
    "horizon": "1-2w",
    "bias": 5,
    "confidence": 81,
    "components": {
      "A_technicals": {
        "score": 25,
        "signals": {
          "rsi14": 54.56,
          "price_vs_sma20_pct": 9.75,
          "price_vs_sma50_pct": 34.82,
          "donchian20_pos_pct": 99.6,
          "bb_width_pct": 50.65
        }
      },
      "B_options_7_21DTE": {
        "score": -5,
        "signals": {
          "nearest_call_wall_dist_pct": 0.69,
          "nearest_put_wall_dist_pct": 10.02,
          "gamma_regime": "negative"
        }
      },
      "C_vol_risk": {
        "score": -10,
        "signals": {
          "iv_to_rv": 0.996,
          "em_2w_to_atr": 1.648,
          "em_pct_1w": 15.38
        }
      },
      "D_volume_tape": {
        "score": -5,
        "signals": {
          "volume_rel_20d_last_close": 0.78
        }
      }
    },
    "rules_triggered": [
      {
        "code": "PX_GT_SMA20",
        "weight": 10,
        "side": 1
      },
      {
        "code": "PX_GT_SMA50",
        "weight": 10,
        "side": 1
      },
      {
        "code": "DONCH_POS_GE_70",
        "weight": 5,
        "side": 1
      },
      {
        "code": "GAMMA_REGIME_NEG",
        "weight": 5,
        "side": -1
      },
      {
        "code": "IV_CHEAP_LT_1_0",
        "weight": 5,
        "side": 1
      },
      {
        "code": "EM2W_ATR_GT_1_6",
        "weight": 10,
        "side": -1
      },
      {
        "code": "BB_WIDTH_GE_12",
        "weight": 5,
        "side": -1
      },
      {
        "code": "VOL_REL_LT_0_9",
        "weight": 5,
        "side": -1
      }
    ],
    "features_flat": {
      "rsi14": 54.56,
      "price_vs_sma20_pct": 9.75,
      "price_vs_sma50_pct": 34.82,
      "donchian20_pos_pct": 99.6484,
      "bb_width_pct": 50.65,
      "nearest_call_wall_dist_pct": 0.69,
      "nearest_put_wall_dist_pct": 10.02,
      "gamma_regime": "negative",
      "iv_to_rv": 0.996,
      "em_2w_to_atr": 1.648,
      "em_pct_1w": 15.38,
      "volume_rel_20d_last_close": 0.78
    },
    "config": {
      "entry_threshold_bias": 55
    }
  },
  "liquidity": {
    "adv20_usd": 3469196976.82,
    "bid_ask": {
      "bid": 233.16,
      "ask": 233.6,
      "mid": 233.38,
      "spread_abs": 0.44,
      "spread_pct": 0.189
    }
  }
}