{
  "symbol": "USAR",
  "latest_price": 14.995,
  "as_of": "2026-07-20T17:38:26.894089+00:00",
  "resistances": [
    {
      "type": "52_week_high",
      "level": 43.98,
      "distance": 193.3,
      "strength_score": 9.0,
      "notes": "Primer test (pendiente) — señal débil (γ-$ bajo)",
      "meta": {
        "level_date": "2025-10-13",
        "atr10": 1.2918,
        "tolerance": 0.2584,
        "retests_since_origin": 0,
        "testing_now": false,
        "low_signal": true,
        "touch_prob_1w": {
          "sigma_pct": 9.0,
          "sigma_source": "em_pct_1w",
          "z": 21.478
        }
      },
      "prob_touch_1w_pct": 0.0,
      "unit": "pct"
    },
    {
      "type": "range_top_3_6m",
      "level": 26.0099,
      "distance": 73.46,
      "strength_score": 8.2,
      "notes": "Techo de rango 3–6m con 2 toques; último 2026-06-22 (pendiente)",
      "meta": {
        "first_touch_date": "2026-04-22",
        "last_touch_date": "2026-06-22",
        "touches": 2,
        "vol_factor_vs_median": 1.63,
        "tolerance": 0.2584,
        "testing_now": false,
        "touch_prob_1w": {
          "sigma_pct": 9.0,
          "sigma_source": "em_pct_1w",
          "z": 8.162
        }
      },
      "prob_touch_1w_pct": 0.0,
      "unit": "pct"
    },
    {
      "type": "gap_down_upper",
      "level": 18.3,
      "distance": 22.04,
      "strength_score": 7.5,
      "notes": "Gap bajista del 2026-07-13 (tam. 1.33%); abierto (pendiente)",
      "meta": {
        "gap_date": "2026-07-13",
        "gap_upper": 18.3,
        "gap_lower": 18.0999,
        "gap_size": 0.2001,
        "gap_size_pct_vs_price": 1.33,
        "vol_factor_vs_median": 0.79,
        "touches_since_gap": 2,
        "last_touch_date": "2026-07-15",
        "tolerance": 0.2584,
        "testing_now": false,
        "filled": false,
        "touch_prob_1w": {
          "sigma_pct": 9.0,
          "sigma_source": "em_pct_1w",
          "z": 2.449
        }
      },
      "prob_touch_1w_pct": 0.7,
      "unit": "pct"
    },
    {
      "type": "avwap_event",
      "level": 21.8228,
      "distance": 45.53,
      "strength_score": 9.2,
      "notes": "AVWAP anclado a gap del 2026-01-29 (pendiente)",
      "meta": {
        "anchor_type": "gap",
        "anchor_date": "2026-01-29",
        "vol_factor_vs_median": 3.57,
        "gap_size_atr": 0.87,
        "touches": null,
        "tolerance": 0.2584,
        "testing_now": false,
        "min_distance_pct": 0.05,
        "method": "daily_typical_price_vwap",
        "touch_prob_1w": {
          "sigma_pct": 9.0,
          "sigma_source": "em_pct_1w",
          "z": 5.059
        }
      },
      "prob_touch_1w_pct": 0.0,
      "unit": "pct"
    },
    {
      "type": "call_wall_gamma",
      "level": 16.0,
      "distance": 6.7,
      "strength_score": 9.6,
      "notes": "Call wall (γ-$) exp 2026-07-24; dominante (37.7% del lado call) — en curso",
      "meta": {
        "expiration": "2026-07-24",
        "gamma_usd": 7.903,
        "gamma_usd_units": "millions",
        "gamma_usd_total_calls": 20.978,
        "gamma_usd_share_pct": 37.7,
        "oi": 1770,
        "oi_share_pct": 6.5,
        "atr10": 1.2918,
        "tolerance": 0.2584,
        "window": "calls agregadas en top 3 expiraciones; sin filtro de distancia",
        "testing_now": true,
        "cluster": {
          "neighbors": [
            15.0,
            15.5,
            16.0,
            16.5,
            17.0
          ],
          "cluster_gamma_usd": 12.627,
          "cluster_share_pct": 60.2
        },
        "method": "sum(|γ|·OI·spot²) por strike multi-exp (sin límites de distancia)",
        "touch_prob_1w": {
          "sigma_pct": 9.0,
          "sigma_source": "em_pct_1w",
          "z": 0.744
        }
      },
      "prob_touch_1w_pct": 22.8,
      "unit": "pct"
    }
  ],
  "supports": [
    {
      "type": "52_week_low",
      "level": 10.91,
      "distance": 27.24,
      "strength_score": 8.5,
      "notes": "Re-test #2 (pendiente)",
      "meta": {
        "level_date": "2025-07-30",
        "atr10": 1.2918,
        "tolerance": 0.2584,
        "retests_since_origin": 1,
        "testing_now": false,
        "touch_prob_1w": {
          "sigma_pct": 9.0,
          "sigma_source": "em_pct_1w",
          "z": 3.027
        }
      },
      "prob_touch_1w_pct": 0.1,
      "unit": "pct"
    },
    {
      "type": "range_bottom_3_6m",
      "level": 13.9675,
      "distance": 6.85,
      "strength_score": 8.0,
      "notes": "Suelo de rango 3–6m con 2 toques; último 2026-04-02 (pendiente)",
      "meta": {
        "first_touch_date": "2026-03-30",
        "last_touch_date": "2026-04-02",
        "touches": 2,
        "vol_factor_vs_median": 0.9,
        "tolerance": 0.2584,
        "testing_now": false,
        "touch_prob_1w": {
          "sigma_pct": 9.0,
          "sigma_source": "em_pct_1w",
          "z": 0.761
        }
      },
      "prob_touch_1w_pct": 22.3,
      "unit": "pct"
    },
    {
      "type": "gap_up_lower",
      "level": 12.6,
      "distance": 15.97,
      "strength_score": 7.0,
      "notes": "Gap alcista del 2025-11-28 (tam. 0.27%); relleno (pendiente)",
      "meta": {
        "gap_date": "2025-11-28",
        "gap_upper": 12.64,
        "gap_lower": 12.6,
        "gap_size": 0.04,
        "gap_size_pct_vs_price": 0.27,
        "vol_factor_vs_median": 0.55,
        "touches_since_gap": 3,
        "last_touch_date": "2025-12-29",
        "tolerance": 0.2584,
        "testing_now": false,
        "filled": true,
        "touch_prob_1w": {
          "sigma_pct": 9.0,
          "sigma_source": "em_pct_1w",
          "z": 1.774
        }
      },
      "prob_touch_1w_pct": 3.8,
      "unit": "pct"
    }
  ],
  "relative_strength": {
    "vs_spy": {
      "20d_diff_pct": -38.79,
      "60d_diff_pct": -45.62
    }
  },
  "call_walls_top": [
    {
      "level": 16.0,
      "expiration": "2026-07-24",
      "gamma_usd_millions": 7.903,
      "gamma_share_pct": 37.7,
      "oi": 1770,
      "oi_share_pct": 6.5,
      "cluster_neighbors": [
        15.0,
        15.5,
        16.0,
        16.5,
        17.0
      ],
      "cluster_gamma_usd": 12.627,
      "cluster_share_pct": 60.2,
      "distance": 6.7
    },
    {
      "level": 17.0,
      "expiration": "2026-07-24",
      "gamma_usd_millions": 2.009,
      "gamma_share_pct": 9.6,
      "oi": 664,
      "oi_share_pct": 2.4,
      "cluster_neighbors": [
        16.0,
        16.5,
        17.0,
        17.5,
        18.0
      ],
      "cluster_gamma_usd": 13.529,
      "cluster_share_pct": 64.5,
      "distance": 13.37
    },
    {
      "level": 18.0,
      "expiration": "2026-07-24",
      "gamma_usd_millions": 1.678,
      "gamma_share_pct": 8.0,
      "oi": 939,
      "oi_share_pct": 3.5,
      "cluster_neighbors": [
        17.0,
        17.5,
        18.0,
        18.5,
        19.0
      ],
      "cluster_gamma_usd": 6.408,
      "cluster_share_pct": 30.5,
      "distance": 20.04
    },
    {
      "level": 20.0,
      "expiration": "2026-07-31",
      "gamma_usd_millions": 1.445,
      "gamma_share_pct": 6.9,
      "oi": 1966,
      "oi_share_pct": 7.2,
      "cluster_neighbors": [
        19.0,
        19.5,
        20.0,
        20.5,
        21.0
      ],
      "cluster_gamma_usd": 3.673,
      "cluster_share_pct": 17.5,
      "distance": 33.38
    },
    {
      "level": 15.0,
      "expiration": "2026-07-24",
      "gamma_usd_millions": 1.086,
      "gamma_share_pct": 5.2,
      "oi": 263,
      "oi_share_pct": 1.0,
      "cluster_neighbors": [
        14.0,
        14.5,
        15.0,
        15.5,
        16.0
      ],
      "cluster_gamma_usd": 9.801,
      "cluster_share_pct": 46.7,
      "distance": 0.03
    }
  ],
  "put_walls_top": [
    {
      "level": 15.0,
      "expiration": "2026-07-24",
      "gamma_usd_millions": 8.826,
      "gamma_share_pct": 25.1,
      "oi": 2158,
      "oi_share_pct": 16.2,
      "cluster_neighbors": [
        14.0,
        14.5,
        15.0,
        15.5,
        16.0
      ],
      "cluster_gamma_usd": 22.579,
      "cluster_share_pct": 64.1,
      "distance": 0.03
    },
    {
      "level": 16.0,
      "expiration": "2026-07-24",
      "gamma_usd_millions": 6.603,
      "gamma_share_pct": 18.7,
      "oi": 1592,
      "oi_share_pct": 11.9,
      "cluster_neighbors": [
        15.0,
        15.5,
        16.0,
        16.5,
        17.0
      ],
      "cluster_gamma_usd": 23.093,
      "cluster_share_pct": 65.6,
      "distance": 6.7
    },
    {
      "level": 17.0,
      "expiration": "2026-07-24",
      "gamma_usd_millions": 4.568,
      "gamma_share_pct": 13.0,
      "oi": 1581,
      "oi_share_pct": 11.8,
      "cluster_neighbors": [
        16.0,
        16.5,
        17.0,
        17.5,
        18.0
      ],
      "cluster_gamma_usd": 15.486,
      "cluster_share_pct": 44.0,
      "distance": 13.37
    },
    {
      "level": 14.0,
      "expiration": "2026-07-31",
      "gamma_usd_millions": 4.324,
      "gamma_share_pct": 12.3,
      "oi": 1358,
      "oi_share_pct": 10.2,
      "cluster_neighbors": [
        13.0,
        13.5,
        14.0,
        14.5,
        15.0
      ],
      "cluster_gamma_usd": 15.829,
      "cluster_share_pct": 44.9,
      "distance": -6.64
    },
    {
      "level": 16.5,
      "expiration": "2026-07-24",
      "gamma_usd_millions": 1.687,
      "gamma_share_pct": 4.8,
      "oi": 491,
      "oi_share_pct": 3.7,
      "cluster_neighbors": [
        15.5,
        16.0,
        16.5,
        17.0,
        17.5
      ],
      "cluster_gamma_usd": 15.562,
      "cluster_share_pct": 44.2,
      "distance": 10.04
    }
  ],
  "technicals": {
    "rsi14": 24.09,
    "sma": {
      "20": 19.1752,
      "50": 22.5197,
      "200": 20.2373
    },
    "bollinger20_2": {
      "upper": 23.845,
      "middle": 19.1752,
      "lower": 14.5055,
      "width_pct": 48.71,
      "method": "SMA20 ± 2·σ(cierre)"
    },
    "keltner_ema20_atr10": {
      "upper": 21.5696,
      "center": 18.986,
      "lower": 16.4025,
      "mult": 2.0,
      "method": "EMA20(typical) ± mult·ATR10"
    },
    "donchian20": {
      "high": 26.0699,
      "low": 14.84
    },
    "atr10": 1.2918,
    "volume": {
      "avg_20d": 10923599.8,
      "median_20d": 10119835.0,
      "avg_dollar_20d": 212548115.91,
      "last_complete_day": {
        "date": "2026-07-20",
        "shares": 7408282,
        "rel_to_20d": 0.678
      },
      "series": {
        "shares_20d": [
          16092035,
          11509871,
          13174198,
          11824525,
          17077477,
          10057289,
          9009269,
          13421949,
          14198950,
          7387873,
          14191352,
          9332473,
          8317806,
          5936834,
          9208711,
          10182381,
          8060085,
          12283332,
          9797304,
          7408282
        ],
        "dollar_volume_20d": [
          388139884.2,
          263460947.19,
          282191321.16,
          244294686.5,
          349575954.19,
          211605360.56,
          194420025.02,
          268170541.02,
          271909892.5,
          142955342.55,
          252322238.56,
          172184126.85,
          156956999.22,
          109712692.32,
          158481916.31,
          185217510.39,
          139520071.35,
          195427812.12,
          153327807.6,
          111087188.59
        ]
      },
      "current_session": {
        "shares": 7405972.0,
        "comparable_to_avg_20d": false
      },
      "note": "ratios calculados contra último día COMPLETO; intradía solo informativo"
    },
    "trend": {
      "above_sma200": false,
      "price_vs_sma": {
        "20": -21.8,
        "50": -33.41,
        "200": -25.9
      },
      "price_20d_change_pct": -39.14,
      "price_50d_change_pct": -47.57,
      "bollinger_pos_pct": 5.2
    }
  },
  "options": {
    "expected_move_1w": {
      "target": "1w",
      "expiration": "2026-07-24",
      "source_expiration": "2026-07-24",
      "dte": 4,
      "weeklyized": false,
      "dollars": 1.35,
      "percent": 9.0,
      "method": "ATM straddle mid (~1W)"
    },
    "max_pain": {
      "expiration": "2026-07-24",
      "strike": 17.0
    },
    "dealer_gamma": {
      "gex_total_usd_millions": -14.251,
      "gamma_regime": "negative",
      "method": "sum_calls_minus_puts"
    },
    "summary_by_expiration": [
      {
        "date": "2026-07-24",
        "dte": 4,
        "atm_iv": 1.075,
        "expected_move": {
          "dollars": 1.35,
          "percent": 0.09,
          "method": "ATM straddle mid"
        },
        "total_call_oi": 18025,
        "total_put_oi": 5445,
        "put_call_oi_ratio": 0.302
      },
      {
        "date": "2026-07-31",
        "dte": 11,
        "atm_iv": 0.958,
        "expected_move": {
          "dollars": 1.995,
          "percent": 0.133,
          "method": "ATM straddle mid"
        },
        "total_call_oi": 9617,
        "total_put_oi": 4459,
        "put_call_oi_ratio": 0.464
      },
      {
        "date": "2026-08-07",
        "dte": 18,
        "atm_iv": 0.9685,
        "expected_move": {
          "dollars": 2.58,
          "percent": 0.1721,
          "method": "ATM straddle mid"
        },
        "total_call_oi": 2148,
        "total_put_oi": 3472,
        "put_call_oi_ratio": 1.616
      }
    ],
    "max_pain_by_expiration": [
      {
        "date": "2026-07-24",
        "strike": 17.0,
        "confidence": 0.001
      },
      {
        "date": "2026-07-31",
        "strike": 19.0,
        "confidence": 0.0
      },
      {
        "date": "2026-08-07",
        "strike": 20.0,
        "confidence": 0.002
      }
    ]
  },
  "options_overview": {
    "put_call_oi_ratio": {
      "near_term": {
        "scope": "near_term",
        "expirations_considered": [
          "2026-07-24",
          "2026-07-31",
          "2026-08-07"
        ],
        "total_put_oi": 13376,
        "total_call_oi": 29790,
        "ratio": 0.449,
        "dte_buckets": {
          "0_7": {
            "puts": 5445,
            "calls": 18025,
            "ratio": 0.302,
            "expirations": [
              "2026-07-24"
            ]
          },
          "8_30": {
            "puts": 7931,
            "calls": 11765,
            "ratio": 0.674,
            "expirations": [
              "2026-07-31",
              "2026-08-07"
            ]
          },
          "31_60": {
            "puts": 0,
            "calls": 0,
            "ratio": null,
            "expirations": []
          },
          "61_plus": {
            "puts": 0,
            "calls": 0,
            "ratio": null,
            "expirations": []
          }
        },
        "per_expiration": [
          {
            "expiration": "2026-07-24",
            "dte": 4,
            "puts": 5445,
            "calls": 18025,
            "ratio": 0.302
          },
          {
            "expiration": "2026-07-31",
            "dte": 11,
            "puts": 4459,
            "calls": 9617,
            "ratio": 0.464
          },
          {
            "expiration": "2026-08-07",
            "dte": 18,
            "puts": 3472,
            "calls": 2148,
            "ratio": 1.616
          }
        ]
      },
      "thru_60d": {
        "scope": "thru_60d",
        "expirations_considered": [
          "2026-07-24",
          "2026-07-31",
          "2026-08-07",
          "2026-08-14",
          "2026-08-21",
          "2026-08-28",
          "2026-09-18"
        ],
        "total_put_oi": 71685,
        "total_call_oi": 126297,
        "ratio": 0.568,
        "dte_buckets": {
          "0_7": {
            "puts": 5445,
            "calls": 18025,
            "ratio": 0.302,
            "expirations": [
              "2026-07-24"
            ]
          },
          "8_30": {
            "puts": 9050,
            "calls": 13293,
            "ratio": 0.681,
            "expirations": [
              "2026-07-31",
              "2026-08-07",
              "2026-08-14"
            ]
          },
          "31_60": {
            "puts": 57190,
            "calls": 94979,
            "ratio": 0.602,
            "expirations": [
              "2026-08-21",
              "2026-08-28",
              "2026-09-18"
            ]
          },
          "61_plus": {
            "puts": 0,
            "calls": 0,
            "ratio": null,
            "expirations": []
          }
        },
        "per_expiration": [
          {
            "expiration": "2026-07-24",
            "dte": 4,
            "puts": 5445,
            "calls": 18025,
            "ratio": 0.302
          },
          {
            "expiration": "2026-07-31",
            "dte": 11,
            "puts": 4459,
            "calls": 9617,
            "ratio": 0.464
          },
          {
            "expiration": "2026-08-07",
            "dte": 18,
            "puts": 3472,
            "calls": 2148,
            "ratio": 1.616
          },
          {
            "expiration": "2026-08-14",
            "dte": 25,
            "puts": 1119,
            "calls": 1528,
            "ratio": 0.732
          },
          {
            "expiration": "2026-08-21",
            "dte": 32,
            "puts": 8453,
            "calls": 15823,
            "ratio": 0.534
          },
          {
            "expiration": "2026-08-28",
            "dte": 39,
            "puts": 890,
            "calls": 1080,
            "ratio": 0.824
          },
          {
            "expiration": "2026-09-18",
            "dte": 60,
            "puts": 47847,
            "calls": 78076,
            "ratio": 0.613
          }
        ]
      },
      "default_scope": "near_term",
      "ratio": 0.449,
      "total_put_oi": 13376,
      "total_call_oi": 29790
    }
  },
  "vols": {
    "rv20_annual_pct": 66.574,
    "rv60_annual_pct": 101.021,
    "rv20_weekly_pct": 9.232,
    "rv60_weekly_pct": 14.009,
    "em_pct_1w": 9.0,
    "em_abs_1w": 1.35,
    "iv_to_rv_ratio": 0.975,
    "em_to_atr_ratio": 1.045,
    "windows": {
      "rv": [
        20,
        60
      ]
    },
    "units": {
      "rv_annual_pct": "percent",
      "rv_weekly_pct": "percent",
      "em_pct_1w": "percent",
      "em_abs_1w": "dollars"
    },
    "method": "std(log_returns_daily) * sqrt(252); weekly = annual/sqrt(52)",
    "em_basis": {
      "source_expiration": "2026-07-24",
      "dte": 4,
      "weeklyized_from_dte": false
    }
  },
  "forward_returns": {
    "lookback_days": 252,
    "series": {
      "anchor_dates": [
        "2025-07-17",
        "2025-07-18",
        "2025-07-21",
        "2025-07-22",
        "2025-07-23",
        "2025-07-24",
        "2025-07-25",
        "2025-07-28",
        "2025-07-29",
        "2025-07-30",
        "2025-07-31",
        "2025-08-01",
        "2025-08-04",
        "2025-08-05",
        "2025-08-06",
        "2025-08-07",
        "2025-08-08",
        "2025-08-11",
        "2025-08-12",
        "2025-08-13",
        "2025-08-14",
        "2025-08-15",
        "2025-08-18",
        "2025-08-19",
        "2025-08-20",
        "2025-08-21",
        "2025-08-22",
        "2025-08-25",
        "2025-08-26",
        "2025-08-27",
        "2025-08-28",
        "2025-08-29",
        "2025-09-02",
        "2025-09-03",
        "2025-09-04",
        "2025-09-05",
        "2025-09-08",
        "2025-09-09",
        "2025-09-10",
        "2025-09-11",
        "2025-09-12",
        "2025-09-15",
        "2025-09-16",
        "2025-09-17",
        "2025-09-18",
        "2025-09-19",
        "2025-09-22",
        "2025-09-23",
        "2025-09-24",
        "2025-09-25",
        "2025-09-26",
        "2025-09-29",
        "2025-09-30",
        "2025-10-01",
        "2025-10-02",
        "2025-10-03",
        "2025-10-06",
        "2025-10-07",
        "2025-10-08",
        "2025-10-09",
        "2025-10-10",
        "2025-10-13",
        "2025-10-14",
        "2025-10-15",
        "2025-10-16",
        "2025-10-17",
        "2025-10-20",
        "2025-10-21",
        "2025-10-22",
        "2025-10-23",
        "2025-10-24",
        "2025-10-27",
        "2025-10-28",
        "2025-10-29",
        "2025-10-30",
        "2025-10-31",
        "2025-11-03",
        "2025-11-04",
        "2025-11-05",
        "2025-11-06",
        "2025-11-07",
        "2025-11-10",
        "2025-11-11",
        "2025-11-12",
        "2025-11-13",
        "2025-11-14",
        "2025-11-17",
        "2025-11-18",
        "2025-11-19",
        "2025-11-20",
        "2025-11-21",
        "2025-11-24",
        "2025-11-25",
        "2025-11-26",
        "2025-11-28",
        "2025-12-01",
        "2025-12-02",
        "2025-12-03",
        "2025-12-04",
        "2025-12-05",
        "2025-12-08",
        "2025-12-09",
        "2025-12-10",
        "2025-12-11",
        "2025-12-12",
        "2025-12-15",
        "2025-12-16",
        "2025-12-17",
        "2025-12-18",
        "2025-12-19",
        "2025-12-22",
        "2025-12-23",
        "2025-12-24",
        "2025-12-26",
        "2025-12-29",
        "2025-12-30",
        "2025-12-31",
        "2026-01-02",
        "2026-01-05",
        "2026-01-06",
        "2026-01-07",
        "2026-01-08",
        "2026-01-09",
        "2026-01-12",
        "2026-01-13",
        "2026-01-14",
        "2026-01-15",
        "2026-01-16",
        "2026-01-20",
        "2026-01-21",
        "2026-01-22",
        "2026-01-23",
        "2026-01-26",
        "2026-01-27",
        "2026-01-28",
        "2026-01-29",
        "2026-01-30",
        "2026-02-02",
        "2026-02-03",
        "2026-02-04",
        "2026-02-05",
        "2026-02-06",
        "2026-02-09",
        "2026-02-10",
        "2026-02-11",
        "2026-02-12",
        "2026-02-13",
        "2026-02-17",
        "2026-02-18",
        "2026-02-19",
        "2026-02-20",
        "2026-02-23",
        "2026-02-24",
        "2026-02-25",
        "2026-02-26",
        "2026-02-27",
        "2026-03-02",
        "2026-03-03",
        "2026-03-04",
        "2026-03-05",
        "2026-03-06",
        "2026-03-09",
        "2026-03-10",
        "2026-03-11",
        "2026-03-12",
        "2026-03-13",
        "2026-03-16",
        "2026-03-17",
        "2026-03-18",
        "2026-03-19",
        "2026-03-20",
        "2026-03-23",
        "2026-03-24",
        "2026-03-25",
        "2026-03-26",
        "2026-03-27",
        "2026-03-30",
        "2026-03-31",
        "2026-04-01",
        "2026-04-02",
        "2026-04-06",
        "2026-04-07",
        "2026-04-08",
        "2026-04-09",
        "2026-04-10",
        "2026-04-13",
        "2026-04-14",
        "2026-04-15",
        "2026-04-16",
        "2026-04-17",
        "2026-04-20",
        "2026-04-21",
        "2026-04-22",
        "2026-04-23",
        "2026-04-24",
        "2026-04-27",
        "2026-04-28",
        "2026-04-29",
        "2026-04-30",
        "2026-05-01",
        "2026-05-04",
        "2026-05-05",
        "2026-05-06",
        "2026-05-07",
        "2026-05-08",
        "2026-05-11",
        "2026-05-12",
        "2026-05-13",
        "2026-05-14",
        "2026-05-15",
        "2026-05-18",
        "2026-05-19",
        "2026-05-20",
        "2026-05-21",
        "2026-05-22",
        "2026-05-26",
        "2026-05-27",
        "2026-05-28",
        "2026-05-29",
        "2026-06-01",
        "2026-06-02",
        "2026-06-03",
        "2026-06-04",
        "2026-06-05",
        "2026-06-08",
        "2026-06-09",
        "2026-06-10",
        "2026-06-11",
        "2026-06-12",
        "2026-06-15",
        "2026-06-16",
        "2026-06-17",
        "2026-06-18",
        "2026-06-22",
        "2026-06-23",
        "2026-06-24",
        "2026-06-25",
        "2026-06-26",
        "2026-06-29",
        "2026-06-30",
        "2026-07-01",
        "2026-07-02",
        "2026-07-06",
        "2026-07-07",
        "2026-07-08",
        "2026-07-09",
        "2026-07-10",
        "2026-07-13",
        "2026-07-14",
        "2026-07-15",
        "2026-07-16",
        "2026-07-17"
      ],
      "t1_dates": [
        "2025-07-18",
        "2025-07-21",
        "2025-07-22",
        "2025-07-23",
        "2025-07-24",
        "2025-07-25",
        "2025-07-28",
        "2025-07-29",
        "2025-07-30",
        "2025-07-31",
        "2025-08-01",
        "2025-08-04",
        "2025-08-05",
        "2025-08-06",
        "2025-08-07",
        "2025-08-08",
        "2025-08-11",
        "2025-08-12",
        "2025-08-13",
        "2025-08-14",
        "2025-08-15",
        "2025-08-18",
        "2025-08-19",
        "2025-08-20",
        "2025-08-21",
        "2025-08-22",
        "2025-08-25",
        "2025-08-26",
        "2025-08-27",
        "2025-08-28",
        "2025-08-29",
        "2025-09-02",
        "2025-09-03",
        "2025-09-04",
        "2025-09-05",
        "2025-09-08",
        "2025-09-09",
        "2025-09-10",
        "2025-09-11",
        "2025-09-12",
        "2025-09-15",
        "2025-09-16",
        "2025-09-17",
        "2025-09-18",
        "2025-09-19",
        "2025-09-22",
        "2025-09-23",
        "2025-09-24",
        "2025-09-25",
        "2025-09-26",
        "2025-09-29",
        "2025-09-30",
        "2025-10-01",
        "2025-10-02",
        "2025-10-03",
        "2025-10-06",
        "2025-10-07",
        "2025-10-08",
        "2025-10-09",
        "2025-10-10",
        "2025-10-13",
        "2025-10-14",
        "2025-10-15",
        "2025-10-16",
        "2025-10-17",
        "2025-10-20",
        "2025-10-21",
        "2025-10-22",
        "2025-10-23",
        "2025-10-24",
        "2025-10-27",
        "2025-10-28",
        "2025-10-29",
        "2025-10-30",
        "2025-10-31",
        "2025-11-03",
        "2025-11-04",
        "2025-11-05",
        "2025-11-06",
        "2025-11-07",
        "2025-11-10",
        "2025-11-11",
        "2025-11-12",
        "2025-11-13",
        "2025-11-14",
        "2025-11-17",
        "2025-11-18",
        "2025-11-19",
        "2025-11-20",
        "2025-11-21",
        "2025-11-24",
        "2025-11-25",
        "2025-11-26",
        "2025-11-28",
        "2025-12-01",
        "2025-12-02",
        "2025-12-03",
        "2025-12-04",
        "2025-12-05",
        "2025-12-08",
        "2025-12-09",
        "2025-12-10",
        "2025-12-11",
        "2025-12-12",
        "2025-12-15",
        "2025-12-16",
        "2025-12-17",
        "2025-12-18",
        "2025-12-19",
        "2025-12-22",
        "2025-12-23",
        "2025-12-24",
        "2025-12-26",
        "2025-12-29",
        "2025-12-30",
        "2025-12-31",
        "2026-01-02",
        "2026-01-05",
        "2026-01-06",
        "2026-01-07",
        "2026-01-08",
        "2026-01-09",
        "2026-01-12",
        "2026-01-13",
        "2026-01-14",
        "2026-01-15",
        "2026-01-16",
        "2026-01-20",
        "2026-01-21",
        "2026-01-22",
        "2026-01-23",
        "2026-01-26",
        "2026-01-27",
        "2026-01-28",
        "2026-01-29",
        "2026-01-30",
        "2026-02-02",
        "2026-02-03",
        "2026-02-04",
        "2026-02-05",
        "2026-02-06",
        "2026-02-09",
        "2026-02-10",
        "2026-02-11",
        "2026-02-12",
        "2026-02-13",
        "2026-02-17",
        "2026-02-18",
        "2026-02-19",
        "2026-02-20",
        "2026-02-23",
        "2026-02-24",
        "2026-02-25",
        "2026-02-26",
        "2026-02-27",
        "2026-03-02",
        "2026-03-03",
        "2026-03-04",
        "2026-03-05",
        "2026-03-06",
        "2026-03-09",
        "2026-03-10",
        "2026-03-11",
        "2026-03-12",
        "2026-03-13",
        "2026-03-16",
        "2026-03-17",
        "2026-03-18",
        "2026-03-19",
        "2026-03-20",
        "2026-03-23",
        "2026-03-24",
        "2026-03-25",
        "2026-03-26",
        "2026-03-27",
        "2026-03-30",
        "2026-03-31",
        "2026-04-01",
        "2026-04-02",
        "2026-04-06",
        "2026-04-07",
        "2026-04-08",
        "2026-04-09",
        "2026-04-10",
        "2026-04-13",
        "2026-04-14",
        "2026-04-15",
        "2026-04-16",
        "2026-04-17",
        "2026-04-20",
        "2026-04-21",
        "2026-04-22",
        "2026-04-23",
        "2026-04-24",
        "2026-04-27",
        "2026-04-28",
        "2026-04-29",
        "2026-04-30",
        "2026-05-01",
        "2026-05-04",
        "2026-05-05",
        "2026-05-06",
        "2026-05-07",
        "2026-05-08",
        "2026-05-11",
        "2026-05-12",
        "2026-05-13",
        "2026-05-14",
        "2026-05-15",
        "2026-05-18",
        "2026-05-19",
        "2026-05-20",
        "2026-05-21",
        "2026-05-22",
        "2026-05-26",
        "2026-05-27",
        "2026-05-28",
        "2026-05-29",
        "2026-06-01",
        "2026-06-02",
        "2026-06-03",
        "2026-06-04",
        "2026-06-05",
        "2026-06-08",
        "2026-06-09",
        "2026-06-10",
        "2026-06-11",
        "2026-06-12",
        "2026-06-15",
        "2026-06-16",
        "2026-06-17",
        "2026-06-18",
        "2026-06-22",
        "2026-06-23",
        "2026-06-24",
        "2026-06-25",
        "2026-06-26",
        "2026-06-29",
        "2026-06-30",
        "2026-07-01",
        "2026-07-02",
        "2026-07-06",
        "2026-07-07",
        "2026-07-08",
        "2026-07-09",
        "2026-07-10",
        "2026-07-13",
        "2026-07-14",
        "2026-07-15",
        "2026-07-16",
        "2026-07-17",
        "2026-07-20"
      ],
      "t1_close_from_close_pct": [
        -5.372,
        -6.43,
        -4.898,
        -2.075,
        -3.454,
        -2.276,
        0.666,
        -8.678,
        0.905,
        13.991,
        9.677,
        0.359,
        1.001,
        -4.812,
        11.822,
        8.112,
        -5.043,
        23.316,
        -10.767,
        4.65,
        -3.318,
        -8.668,
        -5.478,
        -3.841,
        7.008,
        4.06,
        -0.378,
        -0.948,
        0.064,
        -1.721,
        -3.243,
        -6.434,
        -1.433,
        2.544,
        -1.772,
        -2.453,
        4.29,
        -1.631,
        4.758,
        -3.235,
        -2.276,
        8.588,
        4.021,
        5.67,
        -0.915,
        -1.046,
        11.007,
        -6.667,
        9.184,
        -4.755,
        1.241,
        -1.995,
        7.097,
        23.357,
        14.311,
        1.387,
        7.409,
        -4.422,
        14.989,
        4.957,
        18.614,
        -2.934,
        -10.294,
        -15.261,
        -2.838,
        13.92,
        -15.385,
        -8.492,
        -1.676,
        -1.996,
        -8.358,
        -6.806,
        -0.149,
        -2.09,
        -1.169,
        -13.059,
        -3.341,
        3.212,
        -6.224,
        9.735,
        -0.749,
        3.134,
        -4.783,
        -12.234,
        -2.424,
        -0.276,
        5.606,
        -6.291,
        -14.685,
        0.328,
        1.062,
        -2.183,
        2.727,
        8.206,
        -6.394,
        8.34,
        2.786,
        24.679,
        -1.487,
        -0.581,
        2.278,
        -4.397,
        12.127,
        -9.217,
        -12.735,
        0.874,
        -9.6,
        -0.332,
        2.405,
        1.445,
        0.499,
        2.977,
        -7.02,
        -5.996,
        -4.488,
        -1.896,
        18.908,
        11.661,
        10.886,
        -1.884,
        -2.676,
        3.288,
        2.662,
        -6.032,
        9.658,
        -8.151,
        5.36,
        8.536,
        0.677,
        17.486,
        9.071,
        7.872,
        -1.385,
        -4.44,
        -12.351,
        1.586,
        -1.383,
        17.458,
        -9.395,
        -12.452,
        6.019,
        7.326,
        -6.655,
        -0.503,
        -12.356,
        1.651,
        -1.933,
        -4.311,
        1.044,
        -6.308,
        9.054,
        8.515,
        -1.52,
        0.249,
        -6.11,
        10.423,
        -6.948,
        -2.626,
        1.005,
        -8.639,
        7.221,
        9.3,
        3.13,
        -6.354,
        -1.468,
        0.154,
        0.975,
        -6.504,
        -3.207,
        -8.815,
        7.081,
        -4.543,
        0.241,
        -3.846,
        -3.625,
        -7.717,
        6.36,
        -2.213,
        7.568,
        -4.02,
        -4.188,
        14.617,
        -0.358,
        -3.409,
        3.963,
        1.191,
        8.005,
        0.436,
        8.247,
        13.183,
        1.196,
        11.204,
        -9.13,
        -5.327,
        7.548,
        -3.148,
        -3.25,
        17.885,
        1.386,
        -2.848,
        7.193,
        4.303,
        -7.762,
        2.199,
        -2.448,
        -2.852,
        -0.509,
        -2.321,
        -1.772,
        -12.772,
        -6.157,
        13.048,
        7.621,
        4.158,
        9.605,
        -3.714,
        5.581,
        -0.639,
        5.07,
        4.315,
        -8.86,
        -3.145,
        -17.085,
        -1.157,
        -5.898,
        -2.727,
        10.969,
        -2.527,
        4.684,
        -5.56,
        8.326,
        4.628,
        -2.11,
        -5.1,
        -6.422,
        -3.548,
        -0.92,
        2.785,
        2.567,
        -7.414,
        -4.154,
        1.044,
        -8.114,
        3.768,
        2.276,
        -2.067,
        -6.872,
        5.694,
        -4.838,
        -8.088,
        -1.634,
        -4.185
      ],
      "t1_high_from_close_pct": [
        -0.971,
        0.332,
        -2.266,
        1.768,
        1.57,
        2.845,
        0.998,
        1.653,
        3.801,
        15.695,
        10.149,
        8.752,
        10.15,
        2.265,
        12.565,
        11.237,
        6.704,
        27.474,
        2.468,
        7.063,
        -1.406,
        -1.978,
        -3.185,
        0.568,
        9.951,
        7.335,
        6.419,
        5.306,
        2.679,
        4.334,
        3.696,
        -2.347,
        2.436,
        3.125,
        1.626,
        -0.108,
        6.287,
        3.191,
        8.075,
        3.166,
        4.552,
        15.648,
        4.826,
        6.314,
        1.159,
        -0.923,
        12.842,
        3.417,
        14.526,
        -0.715,
        9.726,
        3.193,
        8.493,
        26.942,
        24.395,
        12.096,
        17.477,
        5.235,
        20.614,
        21.822,
        34.867,
        8.583,
        -4.328,
        1.024,
        4.73,
        16.3,
        -5.983,
        -1.048,
        4.166,
        5.946,
        -7.807,
        2.639,
        3.594,
        6.468,
        3.76,
        -2.314,
        2.129,
        6.026,
        0.771,
        10.303,
        2.247,
        5.34,
        4.451,
        1.284,
        1.414,
        3.106,
        8.651,
        3.211,
        2.657,
        1.311,
        2.288,
        -0.808,
        4.132,
        9.493,
        -0.532,
        11.041,
        4.435,
        26.462,
        1.831,
        3.833,
        3.621,
        4.569,
        12.903,
        1.332,
        2.289,
        3.16,
        4.567,
        8.386,
        3.737,
        6.936,
        4.701,
        3.968,
        -0.069,
        0.888,
        0.315,
        0.989,
        21.092,
        14.057,
        15.232,
        5.08,
        2.501,
        7.648,
        5.035,
        8.117,
        10.798,
        -2.833,
        6.015,
        14.581,
        12.702,
        23.383,
        11.273,
        29.471,
        11.115,
        0.266,
        -9.174,
        12.053,
        16.057,
        19.222,
        0.886,
        -1.445,
        6.748,
        8.013,
        1.28,
        4.433,
        -2.389,
        4.714,
        0.748,
        1.63,
        1.319,
        -0.571,
        9.867,
        9.367,
        1.766,
        1.942,
        -2.136,
        11.429,
        -2.205,
        2.472,
        4.178,
        0.995,
        8.367,
        11.379,
        4.866,
        -2.394,
        4.203,
        5.755,
        3.643,
        0.051,
        -1.467,
        1.067,
        9.113,
        -0.345,
        6.024,
        -0.3,
        -0.313,
        3.596,
        6.957,
        4.988,
        10.338,
        1.508,
        0.393,
        15.984,
        2.294,
        8.552,
        5.573,
        5.956,
        10.477,
        2.452,
        13.294,
        18.747,
        7.617,
        13.567,
        -0.236,
        4.244,
        8.737,
        -0.383,
        1.405,
        18.112,
        2.888,
        3.76,
        8.092,
        4.631,
        0.07,
        4.663,
        3.895,
        2.852,
        2.74,
        2.754,
        2.698,
        -0.205,
        -1.34,
        13.949,
        10.545,
        9.96,
        13.123,
        0.216,
        7.079,
        -0.213,
        9.604,
        7.339,
        6.84,
        -1.787,
        -3.875,
        5.874,
        2.206,
        4.45,
        11.412,
        1.418,
        7.776,
        0.261,
        12.649,
        5.265,
        5.803,
        3.876,
        -1.442,
        2.848,
        0.242,
        2.98,
        3.137,
        0.587,
        3.814,
        4.334,
        -1.912,
        4.949,
        4.499,
        1.113,
        -2.057,
        7.263,
        0.758,
        -2.08,
        1.823,
        1.47
      ],
      "t1_close_from_open_pct": [
        -3.721,
        -6.43,
        -2.033,
        -3.044,
        -3.831,
        -1.797,
        -0.165,
        -8.941,
        0.905,
        13.078,
        8.736,
        -5.409,
        0.213,
        -6.92,
        9.065,
        4.164,
        -8.15,
        20.889,
        -11.418,
        6.467,
        -1.828,
        -6.38,
        -2.111,
        -1.246,
        5.895,
        0.506,
        -1.062,
        -0.885,
        0.256,
        -2.897,
        -3.804,
        -3.525,
        -3.099,
        2.469,
        -0.858,
        -1.17,
        3.982,
        -2.871,
        5.596,
        -3.699,
        -3.103,
        2.332,
        5.22,
        4.259,
        -1.619,
        0.5,
        9.644,
        -8.436,
        14.008,
        -3.643,
        -5.952,
        -1.093,
        5.08,
        22.69,
        -0.498,
        -6.0,
        3.743,
        -8.654,
        8.239,
        -4.747,
        0.285,
        -10.586,
        -5.552,
        -15.637,
        7.522,
        6.328,
        -7.828,
        -3.282,
        -4.145,
        -3.914,
        1.171,
        -5.271,
        -0.667,
        -6.286,
        -1.995,
        -10.953,
        1.082,
        2.242,
        -6.832,
        16.902,
        -2.38,
        2.273,
        -4.558,
        -11.607,
        1.329,
        -0.414,
        8.074,
        -7.623,
        -14.145,
        0.369,
        -0.242,
        0.666,
        2.389,
        5.49,
        -5.763,
        7.571,
        3.929,
        24.413,
        4.49,
        -2.227,
        4.506,
        -7.354,
        15.083,
        -7.991,
        -12.581,
        1.798,
        -8.902,
        -1.638,
        3.982,
        -1.022,
        1.002,
        3.786,
        -6.699,
        -3.422,
        -4.338,
        -1.896,
        15.228,
        8.966,
        6.829,
        0.644,
        -0.06,
        0.524,
        0.396,
        -9.254,
        9.658,
        -5.088,
        4.551,
        6.501,
        -2.864,
        13.721,
        4.869,
        -12.565,
        -2.407,
        -4.693,
        -2.818,
        -1.925,
        -8.806,
        10.112,
        -9.812,
        -8.566,
        1.866,
        9.074,
        -5.527,
        -3.715,
        -10.042,
        -0.283,
        -1.195,
        -4.587,
        1.658,
        -3.797,
        10.986,
        11.695,
        -2.192,
        1.105,
        -4.012,
        13.178,
        -0.868,
        -4.253,
        0.105,
        -5.727,
        7.963,
        9.183,
        3.458,
        -3.659,
        -2.991,
        -1.466,
        2.287,
        -5.106,
        -0.056,
        -9.778,
        2.475,
        -2.81,
        -2.747,
        -1.84,
        -2.095,
        -9.276,
        3.416,
        -5.522,
        12.31,
        -2.749,
        -4.251,
        4.809,
        2.076,
        -5.941,
        6.875,
        -2.244,
        5.886,
        -1.497,
        1.682,
        5.514,
        2.65,
        5.087,
        -7.566,
        -9.106,
        8.157,
        0.931,
        -4.217,
        14.759,
        3.498,
        -6.077,
        5.057,
        3.774,
        -7.762,
        -1.064,
        0.229,
        -0.854,
        0.355,
        -3.685,
        2.479,
        -12.521,
        -3.644,
        8.771,
        5.977,
        2.825,
        8.109,
        -2.234,
        6.578,
        0.215,
        5.692,
        0.59,
        -10.593,
        0.259,
        -13.344,
        -6.641,
        -6.152,
        -2.959,
        10.642,
        -3.848,
        -1.202,
        -4.44,
        7.51,
        1.65,
        -3.52,
        2.761,
        -4.715,
        -5.748,
        2.248,
        2.534,
        2.713,
        -5.173,
        -5.151,
        1.362,
        -5.526,
        5.368,
        1.89,
        -1.702,
        -3.923,
        1.62,
        -4.259,
        -5.691,
        1.426,
        -4.063
      ]
    },
    "stats": {
      "close_from_close": {
        "count": 252,
        "mean": 0.249,
        "median": -0.997,
        "up_rate_pct": 44.84,
        "p05": -9.912,
        "p95": 13.515
      },
      "high_from_close": {
        "count": 252,
        "mean": 5.386,
        "median": 3.886,
        "up_rate_pct": 84.13,
        "p05": -2.167,
        "p95": 17.763
      },
      "close_from_open": {
        "count": 252,
        "mean": -0.212,
        "median": -1.042,
        "up_rate_pct": 44.84,
        "p05": -9.793,
        "p95": 11.305
      }
    },
    "latest": {
      "anchor_date": "2026-07-17",
      "t1_date": "2026-07-20",
      "close_from_close_pct": -4.185,
      "high_from_close_pct": 1.47,
      "close_from_open_pct": -4.063
    }
  },
  "conventions": {
    "returns": {
      "basis": "close_to_close",
      "intraday_high_basis": "close_to_high",
      "t_is_trading_days": true
    },
    "probabilities": {
      "touch_1w": "Normal(0, sigma) con sigma = EM 1W (%) si disponible; si no, RV20 semanal (%)"
    }
  },
  "trend_1_2w": {
    "horizon": "1-2w",
    "bias": -45,
    "confidence": 89,
    "components": {
      "A_technicals": {
        "score": -40,
        "signals": {
          "rsi14": 24.09,
          "price_vs_sma20_pct": -21.8,
          "price_vs_sma50_pct": -33.41,
          "donchian20_pos_pct": 1.4,
          "bb_width_pct": 48.71
        }
      },
      "B_options_7_21DTE": {
        "score": 0,
        "signals": {
          "nearest_call_wall_dist_pct": 0.03,
          "nearest_put_wall_dist_pct": 0.0,
          "gamma_regime": "negative"
        }
      },
      "C_vol_risk": {
        "score": 0,
        "signals": {
          "iv_to_rv": 0.975,
          "em_2w_to_atr": 1.045,
          "em_pct_1w": 9.0
        }
      },
      "D_volume_tape": {
        "score": -5,
        "signals": {
          "volume_rel_20d_last_close": 0.678
        }
      }
    },
    "rules_triggered": [
      {
        "code": "RSI_LT_45",
        "weight": 20,
        "side": -1
      },
      {
        "code": "PX_LT_SMA20",
        "weight": 10,
        "side": -1
      },
      {
        "code": "PX_LT_SMA50",
        "weight": 10,
        "side": -1
      },
      {
        "code": "DONCH_POS_LE_30",
        "weight": 5,
        "side": -1
      },
      {
        "code": "PUTWALL_NEAR",
        "weight": 5,
        "side": 1
      },
      {
        "code": "GAMMA_REGIME_NEG",
        "weight": 5,
        "side": -1
      },
      {
        "code": "IV_CHEAP_LT_1_0",
        "weight": 5,
        "side": 1
      },
      {
        "code": "BB_WIDTH_GE_12",
        "weight": 5,
        "side": -1
      },
      {
        "code": "VOL_REL_LT_0_9",
        "weight": 5,
        "side": -1
      }
    ],
    "features_flat": {
      "rsi14": 24.09,
      "price_vs_sma20_pct": -21.8,
      "price_vs_sma50_pct": -33.41,
      "donchian20_pos_pct": 1.3802,
      "bb_width_pct": 48.71,
      "nearest_call_wall_dist_pct": 0.03,
      "nearest_put_wall_dist_pct": 0.0,
      "gamma_regime": "negative",
      "iv_to_rv": 0.975,
      "em_2w_to_atr": 1.045,
      "em_pct_1w": 9.0,
      "volume_rel_20d_last_close": 0.678
    },
    "config": {
      "entry_threshold_bias": 55
    }
  },
  "liquidity": {
    "adv20_usd": 212548115.91,
    "bid_ask": {
      "bid": 14.99,
      "ask": 15.0,
      "mid": 14.995,
      "spread_abs": 0.01,
      "spread_pct": 0.067
    }
  }
}